{
    "schema_version": 3,
    "type": "character",
    "character": {
        "oldId": "-Miw1c9UJIZ_eYDW3P33",
        "name": "Empoleon",
        "avatar": "https://s3.amazonaws.com/files.d20.io/images/272208737/VwDne8ASAWGosSV5OxWCsw/med.jpg?1645502443",
        "bio": "%3Cp%3EEmpoleon%20are%20extremely%20prideful%20and%20believe%20themselves%0Aabove%20others%20who%20are%20not%20a%20part%20of%20their%20families.%20Empoleon%20live%0Ain%20small%20groups.%20While%20each%20member%20retains%20its%20own%20individuality%0Aand%20sense%20of%20self-worth%2C%20they%20have%20learned%20that%20teamwork%20in%0Ahunting%20yields%20far%20superior%20results%20when%20compared%20to%20solitary%0Aattempts.%20The%20Empoleon%20with%20the%20largest%20horns%20on%20their%20heads%0Aare%20the%20leaders%20of%20the%20groups.%20Empoleon%20can%20swim%20quickly%20in%20jet%0Alike%20bursts%2C%20using%20their%20steel-hard%20wings%20to%20slice%20through%20ice%20floes.%0AThey%20are%20too%20proud%20to%20involve%20themselves%20in%20petty%20disputes%2C%20instead%20appearing%20aloof%20in%20most%20conflicts%3B%20however%2C%20they%20will%20viciously%20attack%20anyone%20that%20hurts%20their%20pride%20with%20powerful%20bursts%0Aof%20water%20or%20devastating%20slashes%20with%20their%20wings.%3C/p%3E",
        "gmnotes": "",
        "defaulttoken": "",
        "tags": "[\"Water\",\"Steel\",\"Polar\"]",
        "controlledby": "",
        "inplayerjournals": "",
        "attribs": [
            {
                "name": "atknature",
                "current": 0,
                "max": "",
                "id": "-Miw1cmcFuFrMGxe-dYu"
            },
            {
                "name": "defnature",
                "current": 0,
                "max": "",
                "id": "-Miw1cmhhxkaa2S97xWS"
            },
            {
                "name": "spatknature",
                "current": 0,
                "max": "",
                "id": "-Miw1cmkn2jAv0g5ThML"
            },
            {
                "name": "spdefnature",
                "current": 0,
                "max": "",
                "id": "-Miw1cmnRvPSyMnYuFix"
            },
            {
                "name": "spdnature",
                "current": 0,
                "max": "",
                "id": "-Miw1cmqX9cSZVDSzZ-4"
            },
            {
                "name": "afflictions_text",
                "current": "",
                "max": "",
                "id": "-Miw1cmtU9g_66D38r3F"
            },
            {
                "name": "capture_total",
                "current": 3,
                "max": "",
                "id": "-Miw1cmw7W_aD9UtlsbB"
            },
            {
                "name": "capture_display",
                "current": "+5",
                "max": "",
                "id": "-Miw1cmzcdxmqfUx0MyE"
            },
            {
                "name": "capture_roll_total",
                "current": 5,
                "max": "",
                "id": "-Miw1cn0SUyZonwdqgdH"
            },
            {
                "name": "nature",
                "current": 0,
                "max": "",
                "id": "-Miw1cn2Q1BX9prl2LW5"
            },
            {
                "name": "nature-type",
                "current": "0",
                "max": "",
                "id": "-Miw1cn4PrIcZhL1OQa6"
            },
            {
                "name": "atkbase",
                "current": "9",
                "max": "",
                "id": "-Miw1cn73CC6HZuqK9_x"
            },
            {
                "name": "defbase",
                "current": "10",
                "max": "",
                "id": "-Miw1cn9Nn3n8LamL_G9"
            },
            {
                "name": "spatkbase",
                "current": "11",
                "max": "",
                "id": "-Miw1cnCjipT1TQvA93H"
            },
            {
                "name": "spdefbase",
                "current": "10",
                "max": "",
                "id": "-Miw1cnEM_WSCGgvYSUB"
            },
            {
                "name": "spdbase",
                "current": "6",
                "max": "",
                "id": "-Miw1cnFO3Cg5OluKPbe"
            },
            {
                "name": "acrobatics_total",
                "current": 3,
                "max": "",
                "id": "-Miw1cohIlAyYpRXX-SF"
            },
            {
                "name": "athletics_total",
                "current": 4,
                "max": "",
                "id": "-Miw1colnHwkXt57T33I"
            },
            {
                "name": "bluff_total",
                "current": 5,
                "max": "",
                "id": "-Miw1conTQDR6FdpDAf6"
            },
            {
                "name": "concentration_total",
                "current": 5,
                "max": "",
                "id": "-Miw1coqY7pqDvRG4ZfL"
            },
            {
                "name": "constitution_total",
                "current": 5,
                "max": "",
                "id": "-Miw1cos2dNm1Ub6nlsK"
            },
            {
                "name": "diplomacy_total",
                "current": 5,
                "max": "",
                "id": "-Miw1cov0uwJJ921X_nD"
            },
            {
                "name": "engineering_total",
                "current": 5,
                "max": "",
                "id": "-Miw1coxpEfmABbo-eQT"
            },
            {
                "name": "history_total",
                "current": 5,
                "max": "",
                "id": "-Miw1cp-09tNHLIIM6SM"
            },
            {
                "name": "insight_total",
                "current": 5,
                "max": "",
                "id": "-Miw1cp1FeFLD2zu-gCJ"
            },
            {
                "name": "investigate_total",
                "current": 5,
                "max": "",
                "id": "-Miw1cp3W_wRQIw6SzEV"
            },
            {
                "name": "medicine_total",
                "current": 5,
                "max": "",
                "id": "-Miw1cp66BReNBUsJste"
            },
            {
                "name": "nature_total",
                "current": 5,
                "max": "",
                "id": "-Miw1cp8iKg38Dr7cCEO"
            },
            {
                "name": "perception_total",
                "current": 5,
                "max": "",
                "id": "-Miw1cpBMs3ySXBTsumd"
            },
            {
                "name": "perform_total",
                "current": 5,
                "max": "",
                "id": "-Miw1cpE7DTmr3WUIOE9"
            },
            {
                "name": "handling_total",
                "current": 5,
                "max": "",
                "id": "-Miw1cpHLTR1M6DgzBtR"
            },
            {
                "name": "programming_total",
                "current": 5,
                "max": "",
                "id": "-Miw1cpKRWXFlZkPVQdo"
            },
            {
                "name": "sleightofhand_total",
                "current": 3,
                "max": "",
                "id": "-Miw1cpMXGaZTKGp6AzT"
            },
            {
                "name": "stealth_total",
                "current": 3,
                "max": "",
                "id": "-Miw1cpQzICKnF5qbmdC"
            },
            {
                "name": "selected-page",
                "current": "character-page",
                "max": "",
                "id": "-MiwxuSpIrPdc4DsdULs"
            },
            {
                "name": "character-type",
                "current": "pokemon",
                "max": "",
                "id": "-Miwxuu_KX_vwFzXI9ev"
            },
            {
                "name": "species",
                "current": "Empoleon",
                "max": "",
                "id": "-Miwy1FgEVErwgo84Ia4"
            },
            {
                "name": "type1",
                "current": "water",
                "max": "",
                "id": "-Miwy1ULVGOtWbGIdE5I"
            },
            {
                "name": "type2",
                "current": "steel",
                "max": "",
                "id": "-Miwy1wGHXUwlLEOQkIB"
            },
            {
                "name": "size",
                "current": "Large",
                "max": "",
                "id": "-Miwy3naL2TRzBlpa7RM"
            },
            {
                "name": "weight",
                "current": "Heavy",
                "max": "",
                "id": "-Miwy4UlvkhKq1GdmNUY"
            },
            {
                "name": "egg_group",
                "current": "Water 1/Field-10 days",
                "max": "",
                "id": "-Miwy6hZLHA8suHa4yCo"
            },
            {
                "name": "diet",
                "current": "Omnivore",
                "max": "",
                "id": "-Miwy8k1AkEjJuYM1Nfm"
            },
            {
                "name": "HP",
                "current": "48",
                "max": "48",
                "id": "-Miwy9WdFTXfBXzaOrA7"
            },
            {
                "name": "ATK",
                "current": 9,
                "max": "",
                "id": "-MiwyCE7d7SAl-UloJE8"
            },
            {
                "name": "ATKMOD",
                "current": 4,
                "max": "",
                "id": "-MiwyCEAca0dbDj2wvUS"
            },
            {
                "name": "DEF",
                "current": 10,
                "max": "",
                "id": "-MiwyCVaas7JSbvP8vtV"
            },
            {
                "name": "DEFMOD",
                "current": 5,
                "max": "",
                "id": "-MiwyCVdG_4dyUic9iKw"
            },
            {
                "name": "SPATK",
                "current": 11,
                "max": "",
                "id": "-MiwyCgHnZxMO3S5Kfv8"
            },
            {
                "name": "SPATKMOD",
                "current": 5,
                "max": "",
                "id": "-MiwyCgJf9PDKV3RImJz"
            },
            {
                "name": "SPDEF",
                "current": 10,
                "max": "",
                "id": "-MiwyCyCz8l-ZWcwt06f"
            },
            {
                "name": "SPDEFMOD",
                "current": 5,
                "max": "",
                "id": "-MiwyCyFofz0fqkLnvzq"
            },
            {
                "name": "SPD",
                "current": 6,
                "max": "",
                "id": "-MiwyEXtthds4fzTOnR6"
            },
            {
                "name": "SPDMOD",
                "current": 3,
                "max": "",
                "id": "-MiwyEXwKOaTB7Snz4z9"
            },
            {
                "name": "movement",
                "current": 30,
                "max": "",
                "id": "-MiwyEXy945mAQ2XYosP"
            },
            {
                "name": "pokemonskills",
                "current": "Fountain (can create water)\nSwimmer (can swim)",
                "max": "",
                "id": "-MiwyZzLM0Iy07XLHGou"
            },
            {
                "name": "statpassives",
                "current": "Growl (+1 defense)\n",
                "max": "",
                "id": "-MixFJeAELIsokGkKtoK"
            },
            {
                "name": "otherpassives",
                "current": "Defiant (If a foe lowers any of your stats, you have +2 Attack until your lowered stats are returned to normal.),\nTorrent (When you are below 20 HP, your Water-type attacks deal +4 damage)",
                "max": "",
                "id": "-MixF_toYriaimnRZUtA"
            },
            {
                "name": "repeating_moves_-MixFfL5jrH9Egxd1P7l_move_name",
                "current": "Aqua Jet",
                "max": "",
                "id": "-MixFge6a1A8SS_uk9Rs"
            },
            {
                "name": "repeating_moves_-MixFfL5jrH9Egxd1P7l_move_usage",
                "current": "0",
                "max": "",
                "id": "-MixFgkgsNL8TNRb43qG"
            },
            {
                "name": "repeating_moves_-MixFfL5jrH9Egxd1P7l_move_range",
                "current": "Melee",
                "max": "",
                "id": "-MixFhkUbii4HXg-6zSh"
            },
            {
                "name": "repeating_moves_-MixFfL5jrH9Egxd1P7l_move_type",
                "current": "water",
                "max": "",
                "id": "-MixFii1vymXO2HDnOhN"
            },
            {
                "name": "repeating_moves_-MixFfL5jrH9Egxd1P7l_move_totaldamage",
                "current": 8,
                "max": "",
                "id": "-MixFik0FH3CxKTcE41m"
            },
            {
                "name": "repeating_moves_-MixFfL5jrH9Egxd1P7l_move_totaldamage_display",
                "current": "2d6 + 8",
                "max": "",
                "id": "-MixFik3AaM2K8D-Zh3V"
            },
            {
                "name": "repeating_moves_-MixFfL5jrH9Egxd1P7l_move_category",
                "current": "1",
                "max": "",
                "id": "-MixFjjP3MXvlM9PU3bW"
            },
            {
                "name": "repeating_moves_-MixFfL5jrH9Egxd1P7l_move_category_defense",
                "current": "Defense",
                "max": "",
                "id": "-MixFjlJZNl5M4jPdghR"
            },
            {
                "name": "repeating_moves_-MixFfL5jrH9Egxd1P7l_move_totalaccuracy",
                "current": 4,
                "max": "",
                "id": "-MixFjlOfjfhC8ou3J3i"
            },
            {
                "name": "repeating_moves_-MixFfL5jrH9Egxd1P7l_move_totalaccuracy_display",
                "current": "d20 + 4",
                "max": "",
                "id": "-MixFjlQyF5LOTjilo0J"
            },
            {
                "name": "repeating_moves_-MixFfL5jrH9Egxd1P7l_move_frequency",
                "current": "atwill",
                "max": "",
                "id": "-MixFkYSPtU3zLs9y_lq"
            },
            {
                "name": "repeating_moves_-MixFfL5jrH9Egxd1P7l_move_dicenumber",
                "current": "2",
                "max": "",
                "id": "-MixFliNwDG9RqOEP1Q5"
            },
            {
                "name": "repeating_moves_-MixFfL5jrH9Egxd1P7l_damage_dice",
                "current": "6",
                "max": "",
                "id": "-MixFlng3XlRKo5QoXyK"
            },
            {
                "name": "repeating_moves_-MixFfL5jrH9Egxd1P7l_move_acmod",
                "current": "0",
                "max": "",
                "id": "-MixFn62g3Q7iKVB2wvN"
            },
            {
                "name": "repeating_moves_-MixFfL5jrH9Egxd1P7l_move_effect",
                "current": "Aqua Jet has Priority.",
                "max": "",
                "id": "-MixFrAsCX0wWoF9OPO5"
            },
            {
                "name": "repeating_moves_-MixFfL5jrH9Egxd1P7l_options_flag",
                "current": "0",
                "max": "",
                "id": "-MixFrCJuC5l1iwE7gZ4"
            },
            {
                "name": "repeating_moves_-MixFfL5jrH9Egxd1P7l_flag",
                "current": "+",
                "max": "",
                "id": "-MixFrE0ZDzMY471E00T"
            },
            {
                "name": "repeating_moves_-MixFuMyoZ5LZjHqlD0m_move_name",
                "current": "Brine",
                "max": "",
                "id": "-MixFx4hTVI088K5OFqm"
            },
            {
                "name": "repeating_moves_-MixFuMyoZ5LZjHqlD0m_move_usage",
                "current": "0",
                "max": "",
                "id": "-MixFxCS3_pEwCe60ozU"
            },
            {
                "name": "repeating_moves_-MixFuMyoZ5LZjHqlD0m_move_range",
                "current": "Ranged (20 ft)",
                "max": "",
                "id": "-MixFz4KTTMoOPq4runV"
            },
            {
                "name": "repeating_moves_-MixFuMyoZ5LZjHqlD0m_move_type",
                "current": "water",
                "max": "",
                "id": "-MixFzdhoYmgYS4tMGcf"
            },
            {
                "name": "repeating_moves_-MixFuMyoZ5LZjHqlD0m_move_totaldamage",
                "current": 9,
                "max": "",
                "id": "-MixFzfgyEB15y1Ef4oI"
            },
            {
                "name": "repeating_moves_-MixFuMyoZ5LZjHqlD0m_move_totaldamage_display",
                "current": "3d8 + 9",
                "max": "",
                "id": "-MixFzfiUYEdIKoilDVz"
            },
            {
                "name": "repeating_moves_-MixFuMyoZ5LZjHqlD0m_move_category",
                "current": "2",
                "max": "",
                "id": "-MixFzvuPTYrkGwncGQB"
            },
            {
                "name": "repeating_moves_-MixFuMyoZ5LZjHqlD0m_move_category_defense",
                "current": "Special Defense",
                "max": "",
                "id": "-MixFzxrtBfGzhAA5BBk"
            },
            {
                "name": "repeating_moves_-MixFuMyoZ5LZjHqlD0m_move_totalaccuracy",
                "current": 5,
                "max": "",
                "id": "-MixFzxxvuchYUkeHdHb"
            },
            {
                "name": "repeating_moves_-MixFuMyoZ5LZjHqlD0m_move_totalaccuracy_display",
                "current": "d20 + 5",
                "max": "",
                "id": "-MixFzxzCKSPHs2kWszC"
            },
            {
                "name": "repeating_moves_-MixFuMyoZ5LZjHqlD0m_move_frequency",
                "current": "1day",
                "max": "",
                "id": "-MixG-cJEJF5j83PlVJJ"
            },
            {
                "name": "repeating_moves_-MixFuMyoZ5LZjHqlD0m_move_dicenumber",
                "current": "3",
                "max": "",
                "id": "-MixG0rywrouL8NvyUhB"
            },
            {
                "name": "repeating_moves_-MixFuMyoZ5LZjHqlD0m_damage_dice",
                "current": "8",
                "max": "",
                "id": "-MixG19Gm34r4NlfVVdg"
            },
            {
                "name": "repeating_moves_-MixFuMyoZ5LZjHqlD0m_move_acmod",
                "current": "0",
                "max": "",
                "id": "-MixG2c53aprmNad165S"
            },
            {
                "name": "repeating_moves_-MixFuMyoZ5LZjHqlD0m_move_effect",
                "current": "If the target is at less than half of their Max HP, Brine has [[5d8+9]] for damage instead.",
                "max": "",
                "id": "-MixGEVzOZdsuJ4DfxEY"
            },
            {
                "name": "repeating_moves_-MixFuMyoZ5LZjHqlD0m_options_flag",
                "current": "0",
                "max": "",
                "id": "-MixGEXMe_CEsUwF1cH9"
            },
            {
                "name": "repeating_moves_-MixFuMyoZ5LZjHqlD0m_flag",
                "current": "+",
                "max": "",
                "id": "-MixGEZ6Ja5UVmRuKTb3"
            },
            {
                "name": "repeating_moves_-MixGbRlj1avK4URLfUf_move_name",
                "current": "Drill Peck",
                "max": "",
                "id": "-MixGcbAlZ2SVxKHdA16"
            },
            {
                "name": "repeating_moves_-MixGbRlj1avK4URLfUf_move_usage",
                "current": "0",
                "max": "",
                "id": "-MixGcjcb8F04mhtVZvu"
            },
            {
                "name": "repeating_moves_-MixGbRlj1avK4URLfUf_move_range",
                "current": "Melee",
                "max": "",
                "id": "-MixGdc8VHOEA96VnJq2"
            },
            {
                "name": "repeating_moves_-MixGbRlj1avK4URLfUf_move_type",
                "current": "flying",
                "max": "",
                "id": "-MixGdpGUCK4MWjy1wyK"
            },
            {
                "name": "repeating_moves_-MixGbRlj1avK4URLfUf_move_totaldamage",
                "current": 4,
                "max": "",
                "id": "-MixGdrxuX21bmlYV67n"
            },
            {
                "name": "repeating_moves_-MixGbRlj1avK4URLfUf_move_totaldamage_display",
                "current": "3d10 + 4",
                "max": "",
                "id": "-MixGdrzlPnTiK-ALkIb"
            },
            {
                "name": "repeating_moves_-MixGbRlj1avK4URLfUf_move_category",
                "current": "1",
                "max": "",
                "id": "-MixGeSM9SU1FUylr7OP"
            },
            {
                "name": "repeating_moves_-MixGbRlj1avK4URLfUf_move_category_defense",
                "current": "Defense",
                "max": "",
                "id": "-MixGeUKKNGE_OVQuP7W"
            },
            {
                "name": "repeating_moves_-MixGbRlj1avK4URLfUf_move_totalaccuracy",
                "current": 4,
                "max": "",
                "id": "-MixGeURmFbVRxIMRcKk"
            },
            {
                "name": "repeating_moves_-MixGbRlj1avK4URLfUf_move_totalaccuracy_display",
                "current": "d20 + 4",
                "max": "",
                "id": "-MixGeUTOq2IgmLvdITN"
            },
            {
                "name": "repeating_moves_-MixGbRlj1avK4URLfUf_move_frequency",
                "current": "1day",
                "max": "",
                "id": "-MixGege-DpwWZJbo6an"
            },
            {
                "name": "repeating_moves_-MixGbRlj1avK4URLfUf_move_dicenumber",
                "current": "3",
                "max": "",
                "id": "-MixGf6B4lXTFdLWReZA"
            },
            {
                "name": "repeating_moves_-MixGbRlj1avK4URLfUf_damage_dice",
                "current": "10",
                "max": "",
                "id": "-MixGfBAwmwSeNEvwkmG"
            },
            {
                "name": "repeating_moves_-MixGbRlj1avK4URLfUf_options_flag",
                "current": "0",
                "max": "",
                "id": "-MixGgG65fcXLr43Pa51"
            },
            {
                "name": "repeating_moves_-MixGbRlj1avK4URLfUf_flag",
                "current": "+",
                "max": "",
                "id": "-MixGgHs1ROwAunhQEI2"
            },
            {
                "name": "repeating_moves_-MixHAANZx6IPSrimod-_move_name",
                "current": "Bubble",
                "max": "",
                "id": "-MixHAsEeUg_PMS2Onuc"
            },
            {
                "name": "repeating_moves_-MixHAANZx6IPSrimod-_move_usage",
                "current": "0",
                "max": "",
                "id": "-MixHAyRjm74JfNtX-Su"
            },
            {
                "name": "repeating_moves_-MixHAANZx6IPSrimod-_move_range",
                "current": "Ranged (15 ft)",
                "max": "",
                "id": "-MixHCxSxkFcFmrO9pDM"
            },
            {
                "name": "repeating_moves_-MixHAANZx6IPSrimod-_move_type",
                "current": "water",
                "max": "",
                "id": "-MixHD5iNlqODQjllgAx"
            },
            {
                "name": "repeating_moves_-MixHAANZx6IPSrimod-_move_totaldamage",
                "current": 9,
                "max": "",
                "id": "-MixHD7mzS3XF-C2LOH3"
            },
            {
                "name": "repeating_moves_-MixHAANZx6IPSrimod-_move_totaldamage_display",
                "current": "1d12 + 9",
                "max": "",
                "id": "-MixHD7pFDexunUKdXtJ"
            },
            {
                "name": "repeating_moves_-MixHAANZx6IPSrimod-_move_category",
                "current": "2",
                "max": "",
                "id": "-MixHDkGb3NznUGCW1N3"
            },
            {
                "name": "repeating_moves_-MixHAANZx6IPSrimod-_move_category_defense",
                "current": "Special Defense",
                "max": "",
                "id": "-MixHDmC1HPlZec04NKU"
            },
            {
                "name": "repeating_moves_-MixHAANZx6IPSrimod-_move_totalaccuracy",
                "current": 5,
                "max": "",
                "id": "-MixHDmJUiWIgCye30dU"
            },
            {
                "name": "repeating_moves_-MixHAANZx6IPSrimod-_move_totalaccuracy_display",
                "current": "d20 + 5",
                "max": "",
                "id": "-MixHDmLpuctlF436F98"
            },
            {
                "name": "repeating_moves_-MixHAANZx6IPSrimod-_move_frequency",
                "current": "atwill",
                "max": "",
                "id": "-MixHHBkyhEJZJWxoAjH"
            },
            {
                "name": "repeating_moves_-MixHAANZx6IPSrimod-_move_dicenumber",
                "current": "1",
                "max": "",
                "id": "-MixHIXW8k9Pd1pZ8gOP"
            },
            {
                "name": "repeating_moves_-MixHAANZx6IPSrimod-_damage_dice",
                "current": "12",
                "max": "",
                "id": "-MixHIh0NAKrfwEfubbP"
            },
            {
                "name": "repeating_moves_-MixHAANZx6IPSrimod-_move_acmod",
                "current": "0",
                "max": "",
                "id": "-MixHK1OzUPlpuObJNHz"
            },
            {
                "name": "repeating_moves_-MixHAANZx6IPSrimod-_move_effect",
                "current": "On hit, the target’s Speed is -1 for 10 mins. This effect cannot be stacked.",
                "max": "",
                "id": "-MixHO55u7bIuID0xt3y"
            },
            {
                "name": "repeating_moves_-MixHAANZx6IPSrimod-_options_flag",
                "current": "0",
                "max": "",
                "id": "-MixHO6nPY78-DLQVgif"
            },
            {
                "name": "repeating_moves_-MixHAANZx6IPSrimod-_flag",
                "current": "+",
                "max": "",
                "id": "-MixHO8cf_-KUhW2KbbB"
            },
            {
                "name": "repeating_moves_-MixHOPtgW7gRFmkbfAL_move_name",
                "current": "Metal Claw",
                "max": "",
                "id": "-MixHPd40tNNUwBm1DNc"
            },
            {
                "name": "repeating_moves_-MixHOPtgW7gRFmkbfAL_move_usage",
                "current": "0",
                "max": "",
                "id": "-MixHPjRR8lQdCH_MBN4"
            },
            {
                "name": "repeating_moves_-MixHOPtgW7gRFmkbfAL_move_range",
                "current": "Melee",
                "max": "",
                "id": "-MixHQeCw6NMcVPNu0kE"
            },
            {
                "name": "repeating_moves_-MixHOPtgW7gRFmkbfAL_move_type",
                "current": "steel",
                "max": "",
                "id": "-MixHQlK916ClKvPxUo9"
            },
            {
                "name": "repeating_moves_-MixHOPtgW7gRFmkbfAL_move_totaldamage",
                "current": 8,
                "max": "",
                "id": "-MixHQnRT4rM8c840JGt"
            },
            {
                "name": "repeating_moves_-MixHOPtgW7gRFmkbfAL_move_totaldamage_display",
                "current": "2d6 + 8",
                "max": "",
                "id": "-MixHQnUtlZw9n6_o2Ut"
            },
            {
                "name": "repeating_moves_-MixHOPtgW7gRFmkbfAL_move_category",
                "current": "1",
                "max": "",
                "id": "-MixHR6_vg0TkjHU9u6m"
            },
            {
                "name": "repeating_moves_-MixHOPtgW7gRFmkbfAL_move_category_defense",
                "current": "Defense",
                "max": "",
                "id": "-MixHR8ZlSEbZIqfC4Gf"
            },
            {
                "name": "repeating_moves_-MixHOPtgW7gRFmkbfAL_move_totalaccuracy",
                "current": 4,
                "max": "",
                "id": "-MixHR8hwNR8nTIqQqly"
            },
            {
                "name": "repeating_moves_-MixHOPtgW7gRFmkbfAL_move_totalaccuracy_display",
                "current": "d20 + 4",
                "max": "",
                "id": "-MixHR8jXOSSjcftfpc9"
            },
            {
                "name": "repeating_moves_-MixHOPtgW7gRFmkbfAL_move_frequency",
                "current": "atwill",
                "max": "",
                "id": "-MixHRFnah4ajeNHsTTb"
            },
            {
                "name": "repeating_moves_-MixHOPtgW7gRFmkbfAL_move_dicenumber",
                "current": "2",
                "max": "",
                "id": "-MixHRZoQsaRc3205vas"
            },
            {
                "name": "repeating_moves_-MixHOPtgW7gRFmkbfAL_damage_dice",
                "current": "6",
                "max": "",
                "id": "-MixHRg_Q90HvszgLqfJ"
            },
            {
                "name": "repeating_moves_-MixFfL5jrH9Egxd1P7l_move_effect1_name",
                "current": "",
                "max": "",
                "id": "-MixHStYpfna5m2JRHEM"
            },
            {
                "name": "repeating_moves_-MixFfL5jrH9Egxd1P7l_move_effect2_name",
                "current": "",
                "max": "",
                "id": "-MixHSthCiGX1FXzYIPX"
            },
            {
                "name": "repeating_moves_-MixFuMyoZ5LZjHqlD0m_move_effect1_name",
                "current": "",
                "max": "",
                "id": "-MixHStjDTqJBmwZx-Lz"
            },
            {
                "name": "repeating_moves_-MixFuMyoZ5LZjHqlD0m_move_effect2_name",
                "current": "",
                "max": "",
                "id": "-MixHStmcR2aZSPyRrbm"
            },
            {
                "name": "repeating_moves_-MixGbRlj1avK4URLfUf_move_effect1_name",
                "current": "",
                "max": "",
                "id": "-MixHStrlSu58tCytTFp"
            },
            {
                "name": "repeating_moves_-MixGbRlj1avK4URLfUf_move_effect2_name",
                "current": "",
                "max": "",
                "id": "-MixHStvR3gbcAljSFYh"
            },
            {
                "name": "repeating_moves_-MixHAANZx6IPSrimod-_move_effect1_name",
                "current": "",
                "max": "",
                "id": "-MixHStzqOTAyVRyLmNX"
            },
            {
                "name": "repeating_moves_-MixHAANZx6IPSrimod-_move_effect2_name",
                "current": "",
                "max": "",
                "id": "-MixHSu4gL7TbD47j8fH"
            },
            {
                "name": "repeating_moves_-MixHOPtgW7gRFmkbfAL_move_effect1_name",
                "current": "",
                "max": "",
                "id": "-MixHSu6mgCGHNOs2v3z"
            },
            {
                "name": "repeating_moves_-MixHOPtgW7gRFmkbfAL_move_effect2_name",
                "current": "",
                "max": "",
                "id": "-MixHSu9chMDLvTxaN-B"
            },
            {
                "name": "move_bonusattack",
                "current": "0",
                "max": "",
                "id": "-MixHY8Sa6NV3AExrOj5"
            },
            {
                "name": "repeating_moves_-MixHOPtgW7gRFmkbfAL_move_effect",
                "current": "On hit, your Attack is +1 for 10 mins. This effect cannot be stacked.",
                "max": "",
                "id": "-MixHaxqpILjncAMI3ko"
            },
            {
                "name": "repeating_moves_-MixHOPtgW7gRFmkbfAL_options_flag",
                "current": "0",
                "max": "",
                "id": "-MixHfhqJZhe5-yOdnrI"
            },
            {
                "name": "repeating_moves_-MixHOPtgW7gRFmkbfAL_flag",
                "current": "+",
                "max": "",
                "id": "-MixHfjcOleIwd-uyTh6"
            },
            {
                "name": "repeating_moves_-MixHfvNqv4BZO5NSsUS_move_name",
                "current": "Fury Attack",
                "max": "",
                "id": "-MixHjT8M_VZ9vQ3KiJh"
            },
            {
                "name": "repeating_moves_-MixHfvNqv4BZO5NSsUS_move_usage",
                "current": "0",
                "max": "",
                "id": "-MixHjfP6qkdpeV82rjv"
            },
            {
                "name": "repeating_moves_-MixHfvNqv4BZO5NSsUS_move_range",
                "current": "Melee",
                "max": "",
                "id": "-MixHkQZW_VOC2GX2Bry"
            },
            {
                "name": "repeating_moves_-MixHfvNqv4BZO5NSsUS_move_category",
                "current": "1",
                "max": "",
                "id": "-MixHlMVFw-95nDSBhq1"
            },
            {
                "name": "repeating_moves_-MixHfvNqv4BZO5NSsUS_move_category_defense",
                "current": "Defense",
                "max": "",
                "id": "-MixHlOU0RLqlVbklnqd"
            },
            {
                "name": "repeating_moves_-MixHfvNqv4BZO5NSsUS_move_totaldamage",
                "current": 4,
                "max": "",
                "id": "-MixHlOWgZ8rwNV3rZYy"
            },
            {
                "name": "repeating_moves_-MixHfvNqv4BZO5NSsUS_move_totaldamage_display",
                "current": "1d4 + 4",
                "max": "",
                "id": "-MixHlOYw7Hlhd47bXDd"
            },
            {
                "name": "repeating_moves_-MixHfvNqv4BZO5NSsUS_move_totalaccuracy",
                "current": 2,
                "max": "",
                "id": "-MixHlO_586_2vwk7Eyq"
            },
            {
                "name": "repeating_moves_-MixHfvNqv4BZO5NSsUS_move_totalaccuracy_display",
                "current": "d20 + 2",
                "max": "",
                "id": "-MixHlObKmRnTg_gP2SB"
            },
            {
                "name": "repeating_moves_-MixHfvNqv4BZO5NSsUS_move_frequency",
                "current": "atwill",
                "max": "",
                "id": "-MixHlXcQuwqyOynQ3YI"
            },
            {
                "name": "repeating_moves_-MixHfvNqv4BZO5NSsUS_move_dicenumber",
                "current": "1",
                "max": "",
                "id": "-MixHm9WcRqm9XlCWKwZ"
            },
            {
                "name": "repeating_moves_-MixHfvNqv4BZO5NSsUS_move_effect",
                "current": "Fury Attack has - 2 during Accuracy Check. Fury Attack is a Scatter attack. Up to 5 attacks.\n",
                "max": "",
                "id": "-MixHqoRyx8Ni_EoVex_"
            },
            {
                "name": "repeating_moves_-MixHfvNqv4BZO5NSsUS_move_acmod",
                "current": "-2",
                "max": "",
                "id": "-MixHrXM1PG_HFXcn4J6"
            },
            {
                "name": "repeating_moves_-MixHfvNqv4BZO5NSsUS_move_template",
                "current": "multi-hit-move-roll",
                "max": "",
                "id": "-MixHwhD_JQtgOCZwWpO"
            },
            {
                "name": "repeating_moves_-MixHfvNqv4BZO5NSsUS_options_flag",
                "current": "0",
                "max": "",
                "id": "-MixI-DVhGMGxJNysZy0"
            },
            {
                "name": "repeating_moves_-MixHfvNqv4BZO5NSsUS_flag",
                "current": "+",
                "max": "",
                "id": "-MixI-FLxq9Lm-9SfXJX"
            },
            {
                "name": "repeating_moves_-MixHfvNqv4BZO5NSsUS_move_effect1_name",
                "current": "",
                "max": "",
                "id": "-MixjstiHJACFA-S1uVZ"
            },
            {
                "name": "repeating_moves_-MixHfvNqv4BZO5NSsUS_move_effect2_name",
                "current": "",
                "max": "",
                "id": "-MixjstnTuB-08nNJLDO"
            },
            {
                "name": "pokemon_sex",
                "current": "87.5% male, 12.5% female",
                "max": "",
                "id": "-MwU_o5AL_s93mD_XRTQ"
            },
            {
                "name": "notes",
                "current": "Proficiencies: Ice / Steel (Prinplup / Empoleon) / Water / Avian / Blades (Prinplup / Empoleon)",
                "max": "",
                "id": "-MwUaBxZp7OUlzYkVhMw"
            }
        ],
        "abilities": []
    }
}