{
    "schema_version": 3,
    "type": "character",
    "character": {
        "oldId": "-MwDQyheKVT9vG23L6yx",
        "name": "Jellicent",
        "avatar": "https://s3.amazonaws.com/files.d20.io/images/275927344/xQIA5lJ_sRim-HH6FcZNmg/med.png?1647464788",
        "bio": "%3Cp%3EJellicent%20spend%20much%20of%20their%20time%20in%20the%20deepest%20parts%20of%20the%0Aocean.%20Swarms%20of%20Jellicent%20are%20often%20found%20in%20ocean%20trenches%0Aand%20abysses.%20When%20night%20falls%2C%20Jellicent%20venture%20to%20the%20ocean%u2019s%0Asurface%20to%20feed.%20By%20absorbing%20and%20then%20expelling%20seawater%20from%0Atheir%20bodies%2C%20they%20can%20propel%20themselves%20and%20swim%20about.%20Many%0Aseafaring%20legends%20warn%20of%20Jellicent%20swarms%2C%20cautioning%20that%20no%0Aship%20or%20crew%20has%20ever%20entered%20a%20Jellicent%20habitat%20and%20returned.%0AIndeed%2C%20Jellicent%20do%20seem%20to%20have%20an%20unusual%20affinity%20for%20human%20ships.%20They%20tend%20to%20be%20found%20more%20frequently%20near%20cruise%0Aships%20and%20tankers%20full%20of%20passengers.%20Jellicent%20feed%20on%20life%20force%2C%0Aleaving%20victims%20as%20empty%20husks%20that%20sink%20down%20into%20the%20ocean%0Adepths.%20They%20even%20seem%20to%20congregate%20at%20the%20ocean%27s%20surface%20on%0Anights%20of%20the%20full%20moon%2C%20when%20ships%20are%20most%20plentiful.%20Their%0Acrowns%20are%20thought%20to%20grow%20larger%20the%20more%20life%20force%20they%20consume.%20It%20is%20said%20that%20on%20the%20ocean%20floor%20lies%20a%20Jellicent%20castle%0Amade%20of%20sunken%20shipwrecks.%20%3C/p%3E",
        "gmnotes": "",
        "defaulttoken": "{\"left\":385,\"top\":385,\"width\":70,\"height\":70,\"imgsrc\":\"https://s3.amazonaws.com/files.d20.io/images/275928052/xq8ynHPgEOHyiiTDKFDRTg/med.png?1647465112\",\"page_id\":\"-MYWp6jllc7YsYqj_slP\",\"layer\":\"objects\",\"show_tooltip\":false,\"sides\":\"https%3A//s3.amazonaws.com/files.d20.io/images/275928052/xq8ynHPgEOHyiiTDKFDRTg/med.png%3F1647465112|https%3A//s3.amazonaws.com/files.d20.io/images/275928115/d-ie03Z41xk2p95cnkxxHw/med.png%3F1647465133\",\"lastmove\":\"315,455\"}",
        "tags": "[\"Water\",\"Ghost\",\"Ocean-Abyss\",\"Ocean\"]",
        "controlledby": "",
        "inplayerjournals": "",
        "attribs": [
            {
                "name": "atknature",
                "current": 0,
                "max": "",
                "id": "-MwDQyjXv_Rjjjv5I3qC"
            },
            {
                "name": "defnature",
                "current": 0,
                "max": "",
                "id": "-MwDQyjZwOOkK7P8rStS"
            },
            {
                "name": "spatknature",
                "current": 0,
                "max": "",
                "id": "-MwDQyj_L8kO4sWn4IEY"
            },
            {
                "name": "spdefnature",
                "current": 0,
                "max": "",
                "id": "-MwDQyjaiJy7mSnLN8Ud"
            },
            {
                "name": "spdnature",
                "current": 0,
                "max": "",
                "id": "-MwDQyjaiJy7mSnLN8Ue"
            },
            {
                "name": "afflictions_text",
                "current": "",
                "max": "",
                "id": "-MwDQyjdreYQKMmpUqSN"
            },
            {
                "name": "capture_total",
                "current": 3,
                "max": "",
                "id": "-MwDQyjedEvuNvkG0Uqf"
            },
            {
                "name": "capture_display",
                "current": "+5",
                "max": "",
                "id": "-MwDQyjfVPbFAwrzXURw"
            },
            {
                "name": "capture_roll_total",
                "current": 5,
                "max": "",
                "id": "-MwDQyjgP0F7G3RDFP2B"
            },
            {
                "name": "nature",
                "current": 0,
                "max": "",
                "id": "-MwDQyjh8iaKtP7xcR_P"
            },
            {
                "name": "nature-type",
                "current": "0",
                "max": "",
                "id": "-MwDQyjisir2PqmI-sOS"
            },
            {
                "name": "atkbase",
                "current": "6",
                "max": "",
                "id": "-MwDQyjjosduvtTKo1FI"
            },
            {
                "name": "defbase",
                "current": "7",
                "max": "",
                "id": "-MwDQyjkhDVhf2LUIwTu"
            },
            {
                "name": "spatkbase",
                "current": "9",
                "max": "",
                "id": "-MwDQyjlQhsucpIbWT0R"
            },
            {
                "name": "spdefbase",
                "current": "11",
                "max": "",
                "id": "-MwDQyjmDksdl-XWnVpz"
            },
            {
                "name": "spdbase",
                "current": "6",
                "max": "",
                "id": "-MwDQyjnl5FRio_qeiqr"
            },
            {
                "name": "acrobatics_total",
                "current": 3,
                "max": "",
                "id": "-MwDQyjnl5FRio_qeiqs"
            },
            {
                "name": "athletics_total",
                "current": 3,
                "max": "",
                "id": "-MwDQyjozuHCRk7dW_Mj"
            },
            {
                "name": "bluff_total",
                "current": 5,
                "max": "",
                "id": "-MwDQyjpoaAZngGMR9pX"
            },
            {
                "name": "concentration_total",
                "current": 3,
                "max": "",
                "id": "-MwDQyjpoaAZngGMR9pY"
            },
            {
                "name": "constitution_total",
                "current": 3,
                "max": "",
                "id": "-MwDQyjqQUf6v7C8TN1B"
            },
            {
                "name": "diplomacy_total",
                "current": 5,
                "max": "",
                "id": "-MwDQyjr6qpbNUoxK63r"
            },
            {
                "name": "engineering_total",
                "current": 4,
                "max": "",
                "id": "-MwDQyjsGxRsmvmremRO"
            },
            {
                "name": "history_total",
                "current": 4,
                "max": "",
                "id": "-MwDQyjt9ecW14qbaUvn"
            },
            {
                "name": "insight_total",
                "current": 5,
                "max": "",
                "id": "-MwDQyjua7lrN9VBIrPt"
            },
            {
                "name": "investigate_total",
                "current": 4,
                "max": "",
                "id": "-MwDQyjvRJvdmwAuhPmm"
            },
            {
                "name": "medicine_total",
                "current": 4,
                "max": "",
                "id": "-MwDQyjwQ5UZN6pecU5K"
            },
            {
                "name": "nature_total",
                "current": 4,
                "max": "",
                "id": "-MwDQyjxopLKsF8cHZ5j"
            },
            {
                "name": "perception_total",
                "current": 5,
                "max": "",
                "id": "-MwDQyjy-y3vBLywVVOn"
            },
            {
                "name": "perform_total",
                "current": 5,
                "max": "",
                "id": "-MwDQyjzz_Hlg24du2te"
            },
            {
                "name": "handling_total",
                "current": 5,
                "max": "",
                "id": "-MwDQyk-wA1A3tBP4tyz"
            },
            {
                "name": "programming_total",
                "current": 4,
                "max": "",
                "id": "-MwDQyk-wA1A3tBP4tz-"
            },
            {
                "name": "sleightofhand_total",
                "current": 3,
                "max": "",
                "id": "-MwDQyk0IgscBgMW9Ori"
            },
            {
                "name": "stealth_total",
                "current": 3,
                "max": "",
                "id": "-MwDQyk1zrydTP_eHavq"
            },
            {
                "name": "selected-page",
                "current": "character-page",
                "max": "",
                "id": "-MwDQyk2BL2SqA0TGwBI"
            },
            {
                "name": "character-type",
                "current": "pokemon",
                "max": "",
                "id": "-MwDQyk2BL2SqA0TGwBJ"
            },
            {
                "name": "species",
                "current": "Jellicent",
                "max": "",
                "id": "-MwDQyk3JSlBPw1Szdk_"
            },
            {
                "name": "type1",
                "current": "water",
                "max": "",
                "id": "-MwDQyk48VqRwjGgUUV6"
            },
            {
                "name": "type2",
                "current": "ghost",
                "max": "",
                "id": "-MwDQyk48VqRwjGgUUV7"
            },
            {
                "name": "size",
                "current": "Large",
                "max": "",
                "id": "-MwDQyk5-F4h4bbbFVHZ"
            },
            {
                "name": "weight",
                "current": "Heavy",
                "max": "",
                "id": "-MwDQyk6vjr4UBk-gfKH"
            },
            {
                "name": "pokemon_sex",
                "current": "50% male, 50% female",
                "max": "",
                "id": "-MwDQyk76vXaT5rKfToN"
            },
            {
                "name": "pokemonskills",
                "current": "Flight (can fly)\nFountain (can create water)\nGilled (can breathe underwater)\nStealth (can make stealth skill checks)\nSwimmer (can swim)",
                "max": "",
                "id": "-MwDQyk8uWp3WD7mS2ws"
            },
            {
                "name": "HP",
                "current": "60",
                "max": "60",
                "id": "-MwDQyk9CborSQ3Zqi_V"
            },
            {
                "name": "ATK",
                "current": 6,
                "max": "",
                "id": "-MwDQykAwBlDk2e8CaAv"
            },
            {
                "name": "ATKMOD",
                "current": 3,
                "max": "",
                "id": "-MwDQykBEEQgFsTWEJao"
            },
            {
                "name": "DEF",
                "current": 7,
                "max": "",
                "id": "-MwDQykC_IDMcyuhc7_e"
            },
            {
                "name": "DEFMOD",
                "current": 3,
                "max": "",
                "id": "-MwDQykC_IDMcyuhc7_f"
            },
            {
                "name": "SPATK",
                "current": 9,
                "max": "",
                "id": "-MwDQykDuZouHn_1U62-"
            },
            {
                "name": "SPATKMOD",
                "current": 4,
                "max": "",
                "id": "-MwDQykEeXBLKaTtp2AN"
            },
            {
                "name": "SPDEF",
                "current": 11,
                "max": "",
                "id": "-MwDQykFQmP7u5W5-IwB"
            },
            {
                "name": "SPDEFMOD",
                "current": 5,
                "max": "",
                "id": "-MwDQykGLOtKohsR9lV-"
            },
            {
                "name": "SPD",
                "current": 6,
                "max": "",
                "id": "-MwDQykHz4xhMla4tM1J"
            },
            {
                "name": "SPDMOD",
                "current": 3,
                "max": "",
                "id": "-MwDQykIUd5NzYXUWBpp"
            },
            {
                "name": "movement",
                "current": 30,
                "max": "",
                "id": "-MwDQykK7iWwBEWu3Jar"
            },
            {
                "name": "otherpassives",
                "current": "Cursed Body (When you are hit by a foe’s melee attack, disable that attack for 10 mins. Cursed Body can only affect one attack at a time.)\nDamp (Explosion, Misty Explosion, and Self-Destruct fail to do anything if used within 40ft of you.)\nWater Absorb (When you are hit by a water-type attack, half the damage, then you heal that much HP instead of taking damage.)",
                "max": "",
                "id": "-MwDQykL1j8GxRFbJm4f"
            },
            {
                "name": "repeating_moves_-MjhhKmA7DZfe9B0JHjG_move_name",
                "current": "Bubble",
                "max": "",
                "id": "-MwDQykMTfCLAU1xX7wh"
            },
            {
                "name": "repeating_moves_-MjhhKmA7DZfe9B0JHjG_move_range",
                "current": "Ranged (15 ft)",
                "max": "",
                "id": "-MwDQykMTfCLAU1xX7wi"
            },
            {
                "name": "repeating_moves_-MjhhKmA7DZfe9B0JHjG_move_type",
                "current": "water",
                "max": "",
                "id": "-MwDQykNTZcNUXX1QX1b"
            },
            {
                "name": "repeating_moves_-MjhhKmA7DZfe9B0JHjG_move_totaldamage",
                "current": 8,
                "max": "",
                "id": "-MwDQykP6hL1ymhTY6ha"
            },
            {
                "name": "repeating_moves_-MjhhKmA7DZfe9B0JHjG_move_totaldamage_display",
                "current": "1d12 + 8",
                "max": "",
                "id": "-MwDQykQmUvOH7AX5aFK"
            },
            {
                "name": "repeating_moves_-MjhhKmA7DZfe9B0JHjG_move_category",
                "current": "2",
                "max": "",
                "id": "-MwDQykQmUvOH7AX5aFL"
            },
            {
                "name": "repeating_moves_-MjhhKmA7DZfe9B0JHjG_move_category_defense",
                "current": "Special Defense",
                "max": "",
                "id": "-MwDQykQmUvOH7AX5aFM"
            },
            {
                "name": "repeating_moves_-MjhhKmA7DZfe9B0JHjG_move_totalaccuracy",
                "current": 4,
                "max": "",
                "id": "-MwDQykRcK78JV87sYRZ"
            },
            {
                "name": "repeating_moves_-MjhhKmA7DZfe9B0JHjG_move_totalaccuracy_display",
                "current": "d20 + 4",
                "max": "",
                "id": "-MwDQykSf5yyqFjMVIDx"
            },
            {
                "name": "repeating_moves_-MjhhKmA7DZfe9B0JHjG_move_frequency",
                "current": "atwill",
                "max": "",
                "id": "-MwDQykUb78dQgXQKnt9"
            },
            {
                "name": "repeating_moves_-MjhhKmA7DZfe9B0JHjG_move_dicenumber",
                "current": "1",
                "max": "",
                "id": "-MwDQykVzIfTfoaXqLTt"
            },
            {
                "name": "repeating_moves_-MjhhKmA7DZfe9B0JHjG_damage_dice",
                "current": "12",
                "max": "",
                "id": "-MwDQykW8CcZVNXnS9bt"
            },
            {
                "name": "repeating_moves_-MjhhKmA7DZfe9B0JHjG_move_effect",
                "current": "On hit, the target’s Speed is -1 for 10 mins. This effect cannot be stacked.",
                "max": "",
                "id": "-MwDQykW8CcZVNXnS9bu"
            },
            {
                "name": "repeating_moves_-MjhhKmA7DZfe9B0JHjG_options_flag",
                "current": "0",
                "max": "",
                "id": "-MwDQykXXos-i8IAiFPx"
            },
            {
                "name": "repeating_moves_-MjhhKmA7DZfe9B0JHjG_flag",
                "current": "+",
                "max": "",
                "id": "-MwDQykZ8HZm20H3WUkl"
            },
            {
                "name": "repeating_moves_-MjhhSDCAhRpVRGbQxE4_move_name",
                "current": "Absorb",
                "max": "",
                "id": "-MwDQyk_Cl6ZTXI2kQZj"
            },
            {
                "name": "repeating_moves_-MjhhSDCAhRpVRGbQxE4_move_range",
                "current": "Melee",
                "max": "",
                "id": "-MwDQykabzXeEsr5Uawq"
            },
            {
                "name": "repeating_moves_-MjhhSDCAhRpVRGbQxE4_move_type",
                "current": "grass",
                "max": "",
                "id": "-MwDQykbl8z1De5lIeNl"
            },
            {
                "name": "repeating_moves_-MjhhSDCAhRpVRGbQxE4_move_totaldamage",
                "current": 4,
                "max": "",
                "id": "-MwDQykbl8z1De5lIeNm"
            },
            {
                "name": "repeating_moves_-MjhhSDCAhRpVRGbQxE4_move_totaldamage_display",
                "current": "2d8 + 4",
                "max": "",
                "id": "-MwDQykcuT0DXTkrJM9v"
            },
            {
                "name": "repeating_moves_-MjhhSDCAhRpVRGbQxE4_move_category",
                "current": "2",
                "max": "",
                "id": "-MwDQykebuZOwBv9i25d"
            },
            {
                "name": "repeating_moves_-MjhhSDCAhRpVRGbQxE4_move_category_defense",
                "current": "Special Defense",
                "max": "",
                "id": "-MwDQykf50Ogb7yMewXh"
            },
            {
                "name": "repeating_moves_-MjhhSDCAhRpVRGbQxE4_move_totalaccuracy",
                "current": 4,
                "max": "",
                "id": "-MwDQykgpUH4AEzSwMDI"
            },
            {
                "name": "repeating_moves_-MjhhSDCAhRpVRGbQxE4_move_totalaccuracy_display",
                "current": "d20 + 4",
                "max": "",
                "id": "-MwDQykhT4iuEeoe_cve"
            },
            {
                "name": "repeating_moves_-MjhhSDCAhRpVRGbQxE4_move_frequency",
                "current": "1day",
                "max": "",
                "id": "-MwDQykiURONbnB6cbDJ"
            },
            {
                "name": "repeating_moves_-MjhhSDCAhRpVRGbQxE4_move_dicenumber",
                "current": "2",
                "max": "",
                "id": "-MwDQykjdeL_rDqxpXi_"
            },
            {
                "name": "repeating_moves_-MjhhSDCAhRpVRGbQxE4_damage_dice",
                "current": "8",
                "max": "",
                "id": "-MwDQykjdeL_rDqxpXia"
            },
            {
                "name": "repeating_moves_-MjhhSDCAhRpVRGbQxE4_move_effect",
                "current": "On hit, you regain HP equal to half of the damage dealt.",
                "max": "",
                "id": "-MwDQykki3qLY3Q2GWgc"
            },
            {
                "name": "repeating_moves_-MjhhSDCAhRpVRGbQxE4_options_flag",
                "current": "0",
                "max": "",
                "id": "-MwDQyklZYfV9_pZ30H7"
            },
            {
                "name": "repeating_moves_-MjhhSDCAhRpVRGbQxE4_flag",
                "current": "+",
                "max": "",
                "id": "-MwDQykmvA2Yl5DoNMZX"
            },
            {
                "name": "repeating_moves_-MjhhYT-m9tKf18wbZ6V_move_name",
                "current": "Poison Sting",
                "max": "",
                "id": "-MwDQyknhJ-QmAFp1SmD"
            },
            {
                "name": "repeating_moves_-MjhhYT-m9tKf18wbZ6V_move_range",
                "current": "Melee",
                "max": "",
                "id": "-MwDQykoQi1OuMn7iFxL"
            },
            {
                "name": "repeating_moves_-MjhhYT-m9tKf18wbZ6V_move_type",
                "current": "poison",
                "max": "",
                "id": "-MwDQykoQi1OuMn7iFxM"
            },
            {
                "name": "repeating_moves_-MjhhYT-m9tKf18wbZ6V_move_totaldamage",
                "current": 3,
                "max": "",
                "id": "-MwDQykpkhhSF78D292x"
            },
            {
                "name": "repeating_moves_-MjhhYT-m9tKf18wbZ6V_move_totaldamage_display",
                "current": "1d4 + 3",
                "max": "",
                "id": "-MwDQykqrM4e4eIk9u9u"
            },
            {
                "name": "repeating_moves_-MjhhYT-m9tKf18wbZ6V_move_category",
                "current": "1",
                "max": "",
                "id": "-MwDQykrDZAr45uqr4UY"
            },
            {
                "name": "repeating_moves_-MjhhYT-m9tKf18wbZ6V_move_category_defense",
                "current": "Defense",
                "max": "",
                "id": "-MwDQyksXYBETddJbjzn"
            },
            {
                "name": "repeating_moves_-MjhhYT-m9tKf18wbZ6V_move_totalaccuracy",
                "current": 3,
                "max": "",
                "id": "-MwDQyksXYBETddJbjzo"
            },
            {
                "name": "repeating_moves_-MjhhYT-m9tKf18wbZ6V_move_totalaccuracy_display",
                "current": "d20 + 3",
                "max": "",
                "id": "-MwDQyktQ6k2fkozGujL"
            },
            {
                "name": "repeating_moves_-MjhhYT-m9tKf18wbZ6V_move_frequency",
                "current": "atwill",
                "max": "",
                "id": "-MwDQykuQi_-dps33140"
            },
            {
                "name": "repeating_moves_-MjhhYT-m9tKf18wbZ6V_move_dicenumber",
                "current": "1",
                "max": "",
                "id": "-MwDQykvNo1VcTWCTnPH"
            },
            {
                "name": "repeating_moves_-MjhhYT-m9tKf18wbZ6V_move_effect1_threshold",
                "current": "15",
                "max": "",
                "id": "-MwDQykvNo1VcTWCTnPI"
            },
            {
                "name": "repeating_moves_-MjhhYT-m9tKf18wbZ6V_move_effect1",
                "current": "8",
                "max": "",
                "id": "-MwDQykwRMyGoQL6iR_k"
            },
            {
                "name": "repeating_moves_-MjhhYT-m9tKf18wbZ6V_move_effect1_name",
                "current": "Poisoned",
                "max": "",
                "id": "-MwDQykxEncQXdYU610x"
            },
            {
                "name": "repeating_moves_-MjhhYT-m9tKf18wbZ6V_move_effect2_name",
                "current": "",
                "max": "",
                "id": "-MwDQykyaqmNvg4ijHQh"
            },
            {
                "name": "repeating_moves_-MjhhYT-m9tKf18wbZ6V_options_flag",
                "current": "0",
                "max": "",
                "id": "-MwDQykzLyL5qQ4C43IO"
            },
            {
                "name": "repeating_moves_-MjhhYT-m9tKf18wbZ6V_flag",
                "current": "+",
                "max": "",
                "id": "-MwDQykzLyL5qQ4C43IP"
            },
            {
                "name": "repeating_moves_-MjhhKmA7DZfe9B0JHjG_move_effect1_name",
                "current": "",
                "max": "",
                "id": "-MwDQyl-vOeMKyB5xJjA"
            },
            {
                "name": "repeating_moves_-MjhhKmA7DZfe9B0JHjG_move_effect2_name",
                "current": "",
                "max": "",
                "id": "-MwDQyl0W8FluvJPQTj_"
            },
            {
                "name": "repeating_moves_-MjhhSDCAhRpVRGbQxE4_move_effect1_name",
                "current": "",
                "max": "",
                "id": "-MwDQyl1yhibmpuY-nu4"
            },
            {
                "name": "repeating_moves_-MjhhSDCAhRpVRGbQxE4_move_effect2_name",
                "current": "",
                "max": "",
                "id": "-MwDQyl2suCE_LbtMY06"
            },
            {
                "name": "egg_group",
                "current": "Amorphous/Water 3-10 days",
                "max": "",
                "id": "-MwDQyl2suCE_LbtMY07"
            },
            {
                "name": "diet",
                "current": "Carnivore",
                "max": "",
                "id": "-MwDQyl4ohuTtjJTMd0Q"
            },
            {
                "name": "repeating_moves_-MjhhYT-m9tKf18wbZ6V_move_effect",
                "current": "On hit, if you got 15 or higher on Accuracy Check, the target is Poisoned.",
                "max": "",
                "id": "-MwDQyl5FkIUhsT327cf"
            },
            {
                "name": "notes",
                "current": "Proficiencies: Ghost / Water / Elemental Attack I / Parasitic",
                "max": "",
                "id": "-MwDQyl6kuYmVgicfn1T"
            },
            {
                "name": "repeating_moves_-MwDRVXZTgZDkbTNCTie_move_name",
                "current": "Omnious Wind",
                "max": "",
                "id": "-MwDRWt6K3eB4qgPTffS"
            },
            {
                "name": "repeating_moves_-MwDRVXZTgZDkbTNCTie_move_usage",
                "current": "0",
                "max": "",
                "id": "-MwDRWy6REz2ikJPBDyd"
            },
            {
                "name": "repeating_moves_-MwDRVXZTgZDkbTNCTie_move_range",
                "current": "Ranged (10 ft)",
                "max": "",
                "id": "-MwDRZtLoghy6CmXXPGF"
            },
            {
                "name": "repeating_moves_-MwDRVXZTgZDkbTNCTie_move_type",
                "current": "ghost",
                "max": "",
                "id": "-MwDRb17TGqkBreJOsxn"
            },
            {
                "name": "repeating_moves_-MwDRVXZTgZDkbTNCTie_move_totaldamage",
                "current": 8,
                "max": "",
                "id": "-MwDRb31sxJK7EmClEPG"
            },
            {
                "name": "repeating_moves_-MwDRVXZTgZDkbTNCTie_move_totaldamage_display",
                "current": "2d8 + 8",
                "max": "",
                "id": "-MwDRb35yXQrel5yv-oj"
            },
            {
                "name": "repeating_moves_-MwDRVXZTgZDkbTNCTie_move_category",
                "current": "2",
                "max": "",
                "id": "-MwDRbJgqQp5ZdwOeN3a"
            },
            {
                "name": "repeating_moves_-MwDRVXZTgZDkbTNCTie_move_category_defense",
                "current": "Special Defense",
                "max": "",
                "id": "-MwDRbLf8a0ENjgKepbP"
            },
            {
                "name": "repeating_moves_-MwDRVXZTgZDkbTNCTie_move_totalaccuracy",
                "current": 4,
                "max": "",
                "id": "-MwDRbLlmWWiz3kxLhFp"
            },
            {
                "name": "repeating_moves_-MwDRVXZTgZDkbTNCTie_move_totalaccuracy_display",
                "current": "d20 + 4",
                "max": "",
                "id": "-MwDRbLn4WTNfc0Nulbh"
            },
            {
                "name": "repeating_moves_-MwDRVXZTgZDkbTNCTie_move_frequency",
                "current": "3day",
                "max": "",
                "id": "-MwDRbR6g3gia32Kwm1C"
            },
            {
                "name": "repeating_moves_-MwDRVXZTgZDkbTNCTie_move_dicenumber",
                "current": "2",
                "max": "",
                "id": "-MwDRbcPqFurXg6P4ZG5"
            },
            {
                "name": "repeating_moves_-MwDRVXZTgZDkbTNCTie_damage_dice",
                "current": "8",
                "max": "",
                "id": "-MwDRbgx5u2q5Wr07lvu"
            },
            {
                "name": "repeating_moves_-MwDRVXZTgZDkbTNCTie_move_effect",
                "current": "On hit, your Attack, Special Attack, Defense, Special Defense, and Speed are each raised +1 for 1 hour.\n",
                "max": "",
                "id": "-MwDRe90GG99a1R-PduF"
            },
            {
                "name": "repeating_moves_-MwDRVXZTgZDkbTNCTie_options_flag",
                "current": "0",
                "max": "",
                "id": "-MwDReAUImBLKgUp94hz"
            },
            {
                "name": "repeating_moves_-MwDRVXZTgZDkbTNCTie_flag",
                "current": "+",
                "max": "",
                "id": "-MwDReCF29b02sClTYpj"
            },
            {
                "name": "repeating_moves_-MwDReLc2p932eSajAqd_move_name",
                "current": "Brine",
                "max": "",
                "id": "-MwDReuYZp7Ci0YE6noO"
            },
            {
                "name": "repeating_moves_-MwDReLc2p932eSajAqd_move_usage",
                "current": "0",
                "max": "",
                "id": "-MwDRf-FwyOZoY3nISF-"
            },
            {
                "name": "repeating_moves_-MwDReLc2p932eSajAqd_move_range",
                "current": "Ranged (20 ft)",
                "max": "",
                "id": "-MwDRg2NNZQ_1quCzeL2"
            },
            {
                "name": "repeating_moves_-MwDReLc2p932eSajAqd_move_type",
                "current": "water",
                "max": "",
                "id": "-MwDRgAMQ0GfrK8tAlzs"
            },
            {
                "name": "repeating_moves_-MwDReLc2p932eSajAqd_move_totaldamage",
                "current": 8,
                "max": "",
                "id": "-MwDRgCRqfDoyOB1pxiD"
            },
            {
                "name": "repeating_moves_-MwDReLc2p932eSajAqd_move_totaldamage_display",
                "current": "3d8 + 8",
                "max": "",
                "id": "-MwDRgCUISO3RZrpwW5V"
            },
            {
                "name": "repeating_moves_-MwDReLc2p932eSajAqd_move_category",
                "current": "2",
                "max": "",
                "id": "-MwDRgK-OOW219ip-3Oh"
            },
            {
                "name": "repeating_moves_-MwDReLc2p932eSajAqd_move_category_defense",
                "current": "Special Defense",
                "max": "",
                "id": "-MwDRgLms4d-5D60IWMi"
            },
            {
                "name": "repeating_moves_-MwDReLc2p932eSajAqd_move_totalaccuracy",
                "current": 4,
                "max": "",
                "id": "-MwDRgM1W9yfJVtC6FUS"
            },
            {
                "name": "repeating_moves_-MwDReLc2p932eSajAqd_move_totalaccuracy_display",
                "current": "d20 + 4",
                "max": "",
                "id": "-MwDRgM2nOd9f9DbWNBM"
            },
            {
                "name": "repeating_moves_-MwDReLc2p932eSajAqd_move_frequency",
                "current": "1day",
                "max": "",
                "id": "-MwDRgSmu8H4wyYOA-wg"
            },
            {
                "name": "repeating_moves_-MwDReLc2p932eSajAqd_move_dicenumber",
                "current": "3",
                "max": "",
                "id": "-MwDRga4mrx68luRWue4"
            },
            {
                "name": "repeating_moves_-MwDReLc2p932eSajAqd_damage_dice",
                "current": "8",
                "max": "",
                "id": "-MwDRgeO1ciyifdcr2W3"
            },
            {
                "name": "repeating_moves_-MwDReLc2p932eSajAqd_move_effect",
                "current": "If the target is at less than half of their Max HP, Brine has [[5d8+8]] for damage instead.",
                "max": "",
                "id": "-MwDRkEe39DVXePnDQdL"
            },
            {
                "name": "repeating_moves_-MwDReLc2p932eSajAqd_options_flag",
                "current": "0",
                "max": "",
                "id": "-MwDRkGXRan04DbPG213"
            },
            {
                "name": "repeating_moves_-MwDReLc2p932eSajAqd_flag",
                "current": "+",
                "max": "",
                "id": "-MwDRkINiAom7ZhbQ1Zc"
            },
            {
                "name": "repeating_moves_-MwDRkUmsQ8xkSZTMg0M_move_name",
                "current": "Hex",
                "max": "",
                "id": "-MwDRl47QKilZ_2Oi6UT"
            },
            {
                "name": "repeating_moves_-MwDRkUmsQ8xkSZTMg0M_move_usage",
                "current": "0",
                "max": "",
                "id": "-MwDRl9eKffPc11ZL978"
            },
            {
                "name": "repeating_moves_-MwDRkUmsQ8xkSZTMg0M_move_range",
                "current": "Ranged (15 ft)",
                "max": "",
                "id": "-MwDRmQFYimiJV19yaa0"
            },
            {
                "name": "repeating_moves_-MwDRkUmsQ8xkSZTMg0M_move_type",
                "current": "ghost",
                "max": "",
                "id": "-MwDRmY4KcvZmDyoucQy"
            },
            {
                "name": "repeating_moves_-MwDRkUmsQ8xkSZTMg0M_move_totaldamage",
                "current": 8,
                "max": "",
                "id": "-MwDRm_DYJ6-E2MHNhUd"
            },
            {
                "name": "repeating_moves_-MwDRkUmsQ8xkSZTMg0M_move_totaldamage_display",
                "current": "3d8 + 8",
                "max": "",
                "id": "-MwDRm_FPXrMYkAeRPHe"
            },
            {
                "name": "repeating_moves_-MwDRkUmsQ8xkSZTMg0M_move_category",
                "current": "2",
                "max": "",
                "id": "-MwDRmiqZaqIoXy4kU1O"
            },
            {
                "name": "repeating_moves_-MwDRkUmsQ8xkSZTMg0M_move_category_defense",
                "current": "Special Defense",
                "max": "",
                "id": "-MwDRmknZp98hxgeoVwI"
            },
            {
                "name": "repeating_moves_-MwDRkUmsQ8xkSZTMg0M_move_totalaccuracy",
                "current": 4,
                "max": "",
                "id": "-MwDRmkssl6Ezi12MbHv"
            },
            {
                "name": "repeating_moves_-MwDRkUmsQ8xkSZTMg0M_move_totalaccuracy_display",
                "current": "d20 + 4",
                "max": "",
                "id": "-MwDRmkuEbG4iKtu2NSm"
            },
            {
                "name": "repeating_moves_-MwDRkUmsQ8xkSZTMg0M_move_frequency",
                "current": "1day",
                "max": "",
                "id": "-MwDRmpnu77uLp_wf95c"
            },
            {
                "name": "repeating_moves_-MwDRkUmsQ8xkSZTMg0M_move_dicenumber",
                "current": "3",
                "max": "",
                "id": "-MwDRmwjnLc-_-ae2Im9"
            },
            {
                "name": "repeating_moves_-MwDRkUmsQ8xkSZTMg0M_damage_dice",
                "current": "8",
                "max": "",
                "id": "-MwDRn04K4qnfcPWqhcf"
            },
            {
                "name": "repeating_moves_-MwDRkUmsQ8xkSZTMg0M_move_effect",
                "current": "If the target is afflicted, Hex has [[5d8+8]] for damage instead.\n",
                "max": "",
                "id": "-MwDRqpx3JWKxYYu_RJm"
            },
            {
                "name": "repeating_moves_-MwDRkUmsQ8xkSZTMg0M_options_flag",
                "current": "0",
                "max": "",
                "id": "-MwDRr8LqLDdjy21v24N"
            },
            {
                "name": "repeating_moves_-MwDRkUmsQ8xkSZTMg0M_flag",
                "current": "+",
                "max": "",
                "id": "-MwDRrAM8-nLcggX-OJc"
            },
            {
                "name": "repeating_moves_-MwDRVXZTgZDkbTNCTie_move_effect1_name",
                "current": "",
                "max": "",
                "id": "-MyJYKPofyVH7QHEtKH-"
            },
            {
                "name": "repeating_moves_-MwDRVXZTgZDkbTNCTie_move_effect2_name",
                "current": "",
                "max": "",
                "id": "-MyJYKPsAnWrrK93rLSl"
            },
            {
                "name": "repeating_moves_-MwDReLc2p932eSajAqd_move_effect1_name",
                "current": "",
                "max": "",
                "id": "-MyJYKPvOoe2QYLVQJ02"
            },
            {
                "name": "repeating_moves_-MwDReLc2p932eSajAqd_move_effect2_name",
                "current": "",
                "max": "",
                "id": "-MyJYKPx1cJOjrH6ZKKI"
            },
            {
                "name": "repeating_moves_-MwDRkUmsQ8xkSZTMg0M_move_effect1_name",
                "current": "",
                "max": "",
                "id": "-MyJYKQ-aGGA9GWKnMp7"
            },
            {
                "name": "repeating_moves_-MwDRkUmsQ8xkSZTMg0M_move_effect2_name",
                "current": "",
                "max": "",
                "id": "-MyJYKQ3i02ZPJYFSgUi"
            }
        ],
        "abilities": []
    }
}