{
    "schema_version": 3,
    "type": "character",
    "character": {
        "oldId": "-MvWhhes8R61Rk8GiiCT",
        "name": "Polteageist",
        "avatar": "https://s3.amazonaws.com/files.d20.io/images/275005912/WIQCWh10ymrdfEg4oZ5osQ/med.jpg?1646988030",
        "bio": "%3Cp%3EWhen%20provided%20with%20a%20teapot%2C%20and%20when%20they%20have%20the%0Astrength%20to%20inhabit%20it%2C%20Sinistea%20evolve%20into%20Polteageist.%20To%20defend%0Athemselves%2C%20Polteageist%20will%20launch%20their%20tea%20into%20the%20mouths%20of%0Aattackers%2C%20immediately%20causing%20their%20foes%20to%20feel%20weak%20and%20dizzy.%0AStrong%20chills%20are%20a%20common%20symptom%20of%20Polteageist%20tea%20consumption.%20However%2C%20Polteageist%20will%20willingly%20share%20their%20tea%20with%0Athose%20it%20trusts%20deeply%2C%20and%20tea%20connoisseurs%20relish%20the%20unique%0Aflavor%2C%20aroma%2C%20and%20experience%20that%20only%20Polteageist%20tea%20can%20provide.%20Too%20much%20can%20lead%20to%20an%20upset%20stomach%2C%20however%2C%20Polteageist%20themselves%20are%20quite%20picky%20about%20tea%20and%20will%20frown%0Aupon%20trainers%20that%20display%20unsophisticated%20palates%20when%20it%0Acomes%20to%20brewing%20it.%20These%20Pok%E9mon%20are%20seen%20as%20pests%20in%20the%0Ahospitality%20industry%2C%20as%20they%20will%20commonly%20pose%20as%20ordinary%20pots%0Ain%20hotels%20and%20caf%E9s.%20In%20addition%20to%20creating%20eggs%2C%20they%20also%20can%0Areproduce%20by%20pouring%20some%20of%20themselves%20into%20new%20cups%2C%20making%20infestations%20a%20huge%20issue.%3C/p%3E",
        "gmnotes": "",
        "defaulttoken": "",
        "tags": "[\"Ghost\",\"Urban-Abandoned\",\"Ruin\"]",
        "controlledby": "",
        "inplayerjournals": "",
        "attribs": [
            {
                "name": "atknature",
                "current": 0,
                "max": "",
                "id": "-MvWhhghlzHxfx5myyO7"
            },
            {
                "name": "defnature",
                "current": 0,
                "max": "",
                "id": "-MvWhhgi5zfj2lOsAYXf"
            },
            {
                "name": "spatknature",
                "current": 0,
                "max": "",
                "id": "-MvWhhgk9mLTfmX5jeBB"
            },
            {
                "name": "spdefnature",
                "current": 0,
                "max": "",
                "id": "-MvWhhgmsMHVMNbi9CtL"
            },
            {
                "name": "spdnature",
                "current": 0,
                "max": "",
                "id": "-MvWhhgnFP6dJBcSQPEI"
            },
            {
                "name": "afflictions_text",
                "current": "",
                "max": "",
                "id": "-MvWhhgoT0mOE_CpeGjz"
            },
            {
                "name": "capture_total",
                "current": 3,
                "max": "",
                "id": "-MvWhhgqHUShfsKKYaC6"
            },
            {
                "name": "capture_display",
                "current": "+5",
                "max": "",
                "id": "-MvWhhgrryNF8E7-RKVZ"
            },
            {
                "name": "capture_roll_total",
                "current": 5,
                "max": "",
                "id": "-MvWhhgsa-w8LblaV4Oz"
            },
            {
                "name": "nature",
                "current": 0,
                "max": "",
                "id": "-MvWhhgtEuHb17jx0lCd"
            },
            {
                "name": "nature-type",
                "current": "0",
                "max": "",
                "id": "-MvWhhgw-iEb1re2W0u1"
            },
            {
                "name": "atkbase",
                "current": "7",
                "max": "",
                "id": "-MvWhhgx4JZgayi3QQ-n"
            },
            {
                "name": "defbase",
                "current": "8",
                "max": "",
                "id": "-MvWhhgyXnUkDeLa8dM0"
            },
            {
                "name": "spatkbase",
                "current": "14",
                "max": "",
                "id": "-MvWhhgz9plH_cMR3M_J"
            },
            {
                "name": "spdefbase",
                "current": "11",
                "max": "",
                "id": "-MvWhhh-SryQ8pmoydE-"
            },
            {
                "name": "spdbase",
                "current": "7",
                "max": "",
                "id": "-MvWhhh1edyRjxRLEGBS"
            },
            {
                "name": "acrobatics_total",
                "current": 3,
                "max": "",
                "id": "-MvWhhh2NEE-38bqNvDG"
            },
            {
                "name": "athletics_total",
                "current": 3,
                "max": "",
                "id": "-MvWhhh3wK7FA-G3LYBn"
            },
            {
                "name": "bluff_total",
                "current": 5,
                "max": "",
                "id": "-MvWhhh4vb-uGwnHVg12"
            },
            {
                "name": "concentration_total",
                "current": 4,
                "max": "",
                "id": "-MvWhhh5EAPKFBzv9TT6"
            },
            {
                "name": "constitution_total",
                "current": 4,
                "max": "",
                "id": "-MvWhhh6dJC2aDKCnFrG"
            },
            {
                "name": "diplomacy_total",
                "current": 5,
                "max": "",
                "id": "-MvWhhh7dYJp6ANdtStB"
            },
            {
                "name": "engineering_total",
                "current": 7,
                "max": "",
                "id": "-MvWhhh8WFFgtRcFhg3d"
            },
            {
                "name": "history_total",
                "current": 7,
                "max": "",
                "id": "-MvWhhhACl-nkfTVrbC0"
            },
            {
                "name": "insight_total",
                "current": 5,
                "max": "",
                "id": "-MvWhhhBcwFViZ37-m3L"
            },
            {
                "name": "investigate_total",
                "current": 7,
                "max": "",
                "id": "-MvWhhhCZ1yYFXIRer8q"
            },
            {
                "name": "medicine_total",
                "current": 7,
                "max": "",
                "id": "-MvWhhhEp2G8jwfme1h3"
            },
            {
                "name": "nature_total",
                "current": 7,
                "max": "",
                "id": "-MvWhhhEp2G8jwfme1h4"
            },
            {
                "name": "perception_total",
                "current": 5,
                "max": "",
                "id": "-MvWhhhFIkhd4ZgyI-D2"
            },
            {
                "name": "perform_total",
                "current": 5,
                "max": "",
                "id": "-MvWhhhGcfAzic5wbplb"
            },
            {
                "name": "handling_total",
                "current": 5,
                "max": "",
                "id": "-MvWhhhIAg4Ejjbd9Mw9"
            },
            {
                "name": "programming_total",
                "current": 7,
                "max": "",
                "id": "-MvWhhhJIu_sZH7Epfv7"
            },
            {
                "name": "sleightofhand_total",
                "current": 3,
                "max": "",
                "id": "-MvWhhhKgVWDNIKyInpo"
            },
            {
                "name": "stealth_total",
                "current": 3,
                "max": "",
                "id": "-MvWhhhLRKREygJOOPcz"
            },
            {
                "name": "selected-page",
                "current": "character-page",
                "max": "",
                "id": "-MvWhhhMRDECMr0-u27O"
            },
            {
                "name": "character-type",
                "current": "pokemon",
                "max": "",
                "id": "-MvWhhhNj1rZhPoMF2Gm"
            },
            {
                "name": "species",
                "current": "Polteageist",
                "max": "",
                "id": "-MvWhhhO-1ApRxpAEtq-"
            },
            {
                "name": "type1",
                "current": "ghost",
                "max": "",
                "id": "-MvWhhhPu1-X1I0LJsBF"
            },
            {
                "name": "size",
                "current": "Small",
                "max": "",
                "id": "-MvWhhhR6Py42xYLxvmO"
            },
            {
                "name": "weight",
                "current": "Featherweight",
                "max": "",
                "id": "-MvWhhhS6eoPqXbanRH1"
            },
            {
                "name": "egg_group",
                "current": "Mineral/Amorphous-10 days",
                "max": "",
                "id": "-MvWhhhTYnzAcOmGcnHF"
            },
            {
                "name": "diet",
                "current": "Nullivore/Psiotroph",
                "max": "",
                "id": "-MvWhhhUZxmOMKn8YNvm"
            },
            {
                "name": "HP",
                "current": "36",
                "max": "36",
                "id": "-MvWhhhVgTK4J1iXEBwJ"
            },
            {
                "name": "ATK",
                "current": 7,
                "max": "",
                "id": "-MvWhhhWClJ6_RpsT27u"
            },
            {
                "name": "ATKMOD",
                "current": 3,
                "max": "",
                "id": "-MvWhhhXuEYGBOIy8p6S"
            },
            {
                "name": "DEF",
                "current": 8,
                "max": "",
                "id": "-MvWhhhY2WRDpm0ZBbhX"
            },
            {
                "name": "DEFMOD",
                "current": 4,
                "max": "",
                "id": "-MvWhhhZc29Nxac5rgqk"
            },
            {
                "name": "SPATK",
                "current": 14,
                "max": "",
                "id": "-MvWhhh_ynncOhqUatSQ"
            },
            {
                "name": "SPATKMOD",
                "current": 7,
                "max": "",
                "id": "-MvWhhhbGpUT7sle5XOT"
            },
            {
                "name": "SPDEF",
                "current": 11,
                "max": "",
                "id": "-MvWhhhbGpUT7sle5XOU"
            },
            {
                "name": "SPDEFMOD",
                "current": 5,
                "max": "",
                "id": "-MvWhhhclHNvt2W2_rIA"
            },
            {
                "name": "SPD",
                "current": 7,
                "max": "",
                "id": "-MvWhhhdjG1C_LZKTO2H"
            },
            {
                "name": "SPDMOD",
                "current": 3,
                "max": "",
                "id": "-MvWhhhegEp_vso-7phQ"
            },
            {
                "name": "movement",
                "current": 35,
                "max": "",
                "id": "-MvWhhhegEp_vso-7phR"
            },
            {
                "name": "pokemonskills",
                "current": "Hover (can hover)\nAlluring (attracts others with their aroma)",
                "max": "",
                "id": "-MvWhhhfrTSGRY3dNKes"
            },
            {
                "name": "statpassives",
                "current": "Withdraw (+1 Defense)\nNasty Plot (+1 Special Attack)",
                "max": "",
                "id": "-MvWhhhg4wKlUBrr_VTq"
            },
            {
                "name": "otherpassives",
                "current": "Weak Armor (When you are hit by a melee attack, your Defense is -3 and your Speed is +3 for 10 mins. This does not stack.)\nCursed Body (When you are hit by a foe’s melee attack, disable that attack for 10 mins. Cursed Body can only affect one attack at a time.)",
                "max": "",
                "id": "-MvWhhhhNqD-UoyHai2E"
            },
            {
                "name": "notes",
                "current": "Proficiencies: Dark / Ghost / Psychic / Parasitic / Weird\n",
                "max": "",
                "id": "-MvWhhhiUwTu9ohukDIh"
            },
            {
                "name": "repeating_moves_-MvWhRfDU5MRcRhxp61W_move_name",
                "current": "Astonish",
                "max": "",
                "id": "-MvWhhhiUwTu9ohukDIi"
            },
            {
                "name": "repeating_moves_-MvWhRfDU5MRcRhxp61W_move_usage",
                "current": "0",
                "max": "",
                "id": "-MvWhhhjAVZ9TdyT4Wbc"
            },
            {
                "name": "repeating_moves_-MvWhRfDU5MRcRhxp61W_move_range",
                "current": "Melee",
                "max": "",
                "id": "-MvWhhhk1LTajju0OVCI"
            },
            {
                "name": "repeating_moves_-MvWhRfDU5MRcRhxp61W_move_type",
                "current": "ghost",
                "max": "",
                "id": "-MvWhhhlPTtJyvKf-9JX"
            },
            {
                "name": "repeating_moves_-MvWhRfDU5MRcRhxp61W_move_totaldamage",
                "current": 7,
                "max": "",
                "id": "-MvWhhhlPTtJyvKf-9JY"
            },
            {
                "name": "repeating_moves_-MvWhRfDU5MRcRhxp61W_move_totaldamage_display",
                "current": "1d10 + 7",
                "max": "",
                "id": "-MvWhhhmAvuSW4qjPDjR"
            },
            {
                "name": "repeating_moves_-MvWhRfDU5MRcRhxp61W_move_category",
                "current": "1",
                "max": "",
                "id": "-MvWhhhoMWau39U7I4JK"
            },
            {
                "name": "repeating_moves_-MvWhRfDU5MRcRhxp61W_move_category_defense",
                "current": "Defense",
                "max": "",
                "id": "-MvWhhhpqh5-NMB670dc"
            },
            {
                "name": "repeating_moves_-MvWhRfDU5MRcRhxp61W_move_totalaccuracy",
                "current": 3,
                "max": "",
                "id": "-MvWhhhqnm0yph_3XF_1"
            },
            {
                "name": "repeating_moves_-MvWhRfDU5MRcRhxp61W_move_totalaccuracy_display",
                "current": "d20 + 3",
                "max": "",
                "id": "-MvWhhhqnm0yph_3XF_2"
            },
            {
                "name": "repeating_moves_-MvWhRfDU5MRcRhxp61W_move_frequency",
                "current": "atwill",
                "max": "",
                "id": "-MvWhhhr6zQAM6Rkpv7_"
            },
            {
                "name": "repeating_moves_-MvWhRfDU5MRcRhxp61W_move_dicenumber",
                "current": "1",
                "max": "",
                "id": "-MvWhhhs_jY9PJNKZLR1"
            },
            {
                "name": "repeating_moves_-MvWhRfDU5MRcRhxp61W_damage_dice",
                "current": "10",
                "max": "",
                "id": "-MvWhhhtPslry8kQSfcI"
            },
            {
                "name": "repeating_moves_-MvWhRfDU5MRcRhxp61W_move_effect",
                "current": "On hit, if you got 18 or higher on Accuracy Check, the target is Stunned.",
                "max": "",
                "id": "-MvWhhhuobkvLMGyBhn-"
            },
            {
                "name": "repeating_moves_-MvWhRfDU5MRcRhxp61W_move_effect1_threshold",
                "current": "18",
                "max": "",
                "id": "-MvWhhhuobkvLMGyBhn0"
            },
            {
                "name": "repeating_moves_-MvWhRfDU5MRcRhxp61W_move_effect1",
                "current": "10",
                "max": "",
                "id": "-MvWhhhwyjTskyud_AVj"
            },
            {
                "name": "repeating_moves_-MvWhRfDU5MRcRhxp61W_move_effect1_name",
                "current": "Stunned",
                "max": "",
                "id": "-MvWhhhxOHX0V0vVy1Hr"
            },
            {
                "name": "repeating_moves_-MvWhRfDU5MRcRhxp61W_move_effect2_name",
                "current": "",
                "max": "",
                "id": "-MvWhhhyURj7DaGkmDbQ"
            },
            {
                "name": "repeating_moves_-MvWhRfDU5MRcRhxp61W_options_flag",
                "current": "0",
                "max": "",
                "id": "-MvWhhhyURj7DaGkmDbR"
            },
            {
                "name": "repeating_moves_-MvWhRfDU5MRcRhxp61W_flag",
                "current": "+",
                "max": "",
                "id": "-MvWhhhzaMpPLgqGFEIg"
            },
            {
                "name": "repeating_moves_-MvWhXIGFzbdBzrOJjty_move_name",
                "current": "Mega Drain",
                "max": "",
                "id": "-MvWhhi-eNOrjpJn3wz3"
            },
            {
                "name": "repeating_moves_-MvWhXIGFzbdBzrOJjty_move_usage",
                "current": "0",
                "max": "",
                "id": "-MvWhhi0HcWdN51eVz6q"
            },
            {
                "name": "repeating_moves_-MvWhXIGFzbdBzrOJjty_move_range",
                "current": "Melee",
                "max": "",
                "id": "-MvWhhi0HcWdN51eVz6r"
            },
            {
                "name": "repeating_moves_-MvWhXIGFzbdBzrOJjty_move_type",
                "current": "grass",
                "max": "",
                "id": "-MvWhhi1boRBFLyuqPNw"
            },
            {
                "name": "repeating_moves_-MvWhXIGFzbdBzrOJjty_move_totaldamage",
                "current": 7,
                "max": "",
                "id": "-MvWhhi2cX2sh8KJJgqq"
            },
            {
                "name": "repeating_moves_-MvWhXIGFzbdBzrOJjty_move_totaldamage_display",
                "current": "2d10 + 7",
                "max": "",
                "id": "-MvWhhi3MvCKUdDfWKeg"
            },
            {
                "name": "repeating_moves_-MvWhXIGFzbdBzrOJjty_move_category",
                "current": "2",
                "max": "",
                "id": "-MvWhhi419xmmM41enHI"
            },
            {
                "name": "repeating_moves_-MvWhXIGFzbdBzrOJjty_move_category_defense",
                "current": "Special Defense",
                "max": "",
                "id": "-MvWhhi5u0koKeFGIcUG"
            },
            {
                "name": "repeating_moves_-MvWhXIGFzbdBzrOJjty_move_totalaccuracy",
                "current": 7,
                "max": "",
                "id": "-MvWhhi6D_AAPVKcsCdn"
            },
            {
                "name": "repeating_moves_-MvWhXIGFzbdBzrOJjty_move_totalaccuracy_display",
                "current": "d20 + 7",
                "max": "",
                "id": "-MvWhhi8r_tPxEdQ-7v_"
            },
            {
                "name": "repeating_moves_-MvWhXIGFzbdBzrOJjty_move_frequency",
                "current": "1day",
                "max": "",
                "id": "-MvWhhi9d_xccx8-xZ4T"
            },
            {
                "name": "repeating_moves_-MvWhXIGFzbdBzrOJjty_move_dicenumber",
                "current": "2",
                "max": "",
                "id": "-MvWhhiAHdvs6uUv_yRH"
            },
            {
                "name": "repeating_moves_-MvWhXIGFzbdBzrOJjty_damage_dice",
                "current": "10",
                "max": "",
                "id": "-MvWhhiAHdvs6uUv_yRI"
            },
            {
                "name": "repeating_moves_-MvWhXIGFzbdBzrOJjty_move_effect",
                "current": "On hit, you regain HP equal to half of the damage dealt.",
                "max": "",
                "id": "-MvWhhiCKkJgMMVyxvLY"
            },
            {
                "name": "repeating_moves_-MvWhXIGFzbdBzrOJjty_options_flag",
                "current": "0",
                "max": "",
                "id": "-MvWhhiD_EilKLU9tAj0"
            },
            {
                "name": "repeating_moves_-MvWhXIGFzbdBzrOJjty_flag",
                "current": "+",
                "max": "",
                "id": "-MvWhhiEKuN0LGsw7oNz"
            },
            {
                "name": "repeating_moves_-MvWhb3rizPjPyQQ00Qt_move_name",
                "current": "Protect",
                "max": "",
                "id": "-MvWhhiFX-iSSw-s_FIc"
            },
            {
                "name": "repeating_moves_-MvWhb3rizPjPyQQ00Qt_move_usage",
                "current": "0",
                "max": "",
                "id": "-MvWhhiGVVPoma5cHGhl"
            },
            {
                "name": "repeating_moves_-MvWhb3rizPjPyQQ00Qt_move_range",
                "current": "Self",
                "max": "",
                "id": "-MvWhhiIdLQTsEzOstOn"
            },
            {
                "name": "repeating_moves_-MvWhb3rizPjPyQQ00Qt_move_category",
                "current": "3",
                "max": "",
                "id": "-MvWhhiIdLQTsEzOstOo"
            },
            {
                "name": "repeating_moves_-MvWhb3rizPjPyQQ00Qt_move_category_defense",
                "current": "Speed",
                "max": "",
                "id": "-MvWhhiKe4ogPGNHf7rk"
            },
            {
                "name": "repeating_moves_-MvWhb3rizPjPyQQ00Qt_move_totaldamage",
                "current": 0,
                "max": "",
                "id": "-MvWhhiKe4ogPGNHf7rl"
            },
            {
                "name": "repeating_moves_-MvWhb3rizPjPyQQ00Qt_move_totaldamage_display",
                "current": "0",
                "max": "",
                "id": "-MvWhhiLkduXJ-FIdWi4"
            },
            {
                "name": "repeating_moves_-MvWhb3rizPjPyQQ00Qt_move_totalaccuracy",
                "current": 3,
                "max": "",
                "id": "-MvWhhiMaACNcOJzxJsZ"
            },
            {
                "name": "repeating_moves_-MvWhb3rizPjPyQQ00Qt_move_totalaccuracy_display",
                "current": "d20 + 3",
                "max": "",
                "id": "-MvWhhiNKARpmNXegzVQ"
            },
            {
                "name": "repeating_moves_-MvWhb3rizPjPyQQ00Qt_move_frequency",
                "current": "3day",
                "max": "",
                "id": "-MvWhhiNKARpmNXegzVR"
            },
            {
                "name": "repeating_moves_-MvWhb3rizPjPyQQ00Qt_move_effect",
                "current": "Protect is used as a Reaction. When you would be hit by a move, use Protect to instead ignore the damage and any effects of the attack. ",
                "max": "",
                "id": "-MvWhhiOAr9JGyONCGAj"
            },
            {
                "name": "repeating_moves_-MvWhb3rizPjPyQQ00Qt_options_flag",
                "current": "0",
                "max": "",
                "id": "-MvWhhiPqUz3syj9Whut"
            },
            {
                "name": "repeating_moves_-MvWhb3rizPjPyQQ00Qt_flag",
                "current": "+",
                "max": "",
                "id": "-MvWhhiR4mSFOoYeM5FJ"
            },
            {
                "name": "repeating_moves_-MvWhXIGFzbdBzrOJjty_move_effect1_name",
                "current": "",
                "max": "",
                "id": "-MvWhvzt6AB6KdJytlaD"
            },
            {
                "name": "repeating_moves_-MvWhXIGFzbdBzrOJjty_move_effect2_name",
                "current": "",
                "max": "",
                "id": "-MvWhvzyu3-DBTrvC8Tu"
            },
            {
                "name": "repeating_moves_-MvWhb3rizPjPyQQ00Qt_move_effect1_name",
                "current": "",
                "max": "",
                "id": "-MvWhw-2M4BlXnOx8_sE"
            },
            {
                "name": "repeating_moves_-MvWhb3rizPjPyQQ00Qt_move_effect2_name",
                "current": "",
                "max": "",
                "id": "-MvWhw-7SBX9_KdHJyMC"
            },
            {
                "name": "repeating_moves_-MvWiLfNCOhDyxWI97iG_move_name",
                "current": "Curse",
                "max": "",
                "id": "-MvWiMKVNvTHKyn4lJPq"
            },
            {
                "name": "repeating_moves_-MvWiLfNCOhDyxWI97iG_move_usage",
                "current": "0",
                "max": "",
                "id": "-MvWiMP_CJ_vH-4KMtBs"
            },
            {
                "name": "repeating_moves_-MvWiLfNCOhDyxWI97iG_move_range",
                "current": "Ranged (20 ft)",
                "max": "",
                "id": "-MvWiN_RC3LZ3453C41c"
            },
            {
                "name": "repeating_moves_-MvWiLfNCOhDyxWI97iG_move_type",
                "current": "ghost",
                "max": "",
                "id": "-MvWiNeET4eVcMjF5gND"
            },
            {
                "name": "repeating_moves_-MvWiLfNCOhDyxWI97iG_move_totaldamage",
                "current": 0,
                "max": "",
                "id": "-MvWiNgDMgVWKwchtVHI"
            },
            {
                "name": "repeating_moves_-MvWiLfNCOhDyxWI97iG_move_totaldamage_display",
                "current": "0",
                "max": "",
                "id": "-MvWiNgIlDXq3FCcKW_8"
            },
            {
                "name": "repeating_moves_-MvWiLfNCOhDyxWI97iG_move_category",
                "current": "3",
                "max": "",
                "id": "-MvWiNmKNEOlBgxHFY6b"
            },
            {
                "name": "repeating_moves_-MvWiLfNCOhDyxWI97iG_move_category_defense",
                "current": "Speed",
                "max": "",
                "id": "-MvWiNoDoJtBA5bjcfKy"
            },
            {
                "name": "repeating_moves_-MvWiLfNCOhDyxWI97iG_move_totalaccuracy",
                "current": 3,
                "max": "",
                "id": "-MvWiNoJRWurwJKTSau1"
            },
            {
                "name": "repeating_moves_-MvWiLfNCOhDyxWI97iG_move_totalaccuracy_display",
                "current": "d20 + 3",
                "max": "",
                "id": "-MvWiNoOZuKOLv9KOvlc"
            },
            {
                "name": "repeating_moves_-MvWiLfNCOhDyxWI97iG_move_frequency",
                "current": "3day",
                "max": "",
                "id": "-MvWiNt4vwtgmEf79RR-"
            },
            {
                "name": "repeating_moves_-MvWiLfNCOhDyxWI97iG_move_effect",
                "current": "On hit, the target’s Special Defense is -1 for 10 mins. This effect cannot be stacked.",
                "max": "",
                "id": "-MvWiU_Pfsi1QNIqZoFG"
            },
            {
                "name": "repeating_moves_-MvWiLfNCOhDyxWI97iG_options_flag",
                "current": "0",
                "max": "",
                "id": "-MvWiUb02-3-PYZJr9If"
            },
            {
                "name": "repeating_moves_-MvWiLfNCOhDyxWI97iG_flag",
                "current": "+",
                "max": "",
                "id": "-MvWiUctnV4Tr0m6CTMX"
            },
            {
                "name": "repeating_moves_-MvWiV2UP-Mv0tZiLep1_move_name",
                "current": "Shadow Ball",
                "max": "",
                "id": "-MvWiWNwn9QI7egs5nVn"
            },
            {
                "name": "repeating_moves_-MvWiV2UP-Mv0tZiLep1_move_usage",
                "current": "0",
                "max": "",
                "id": "-MvWiWU3KikcsU5G9KCr"
            },
            {
                "name": "repeating_moves_-MvWiV2UP-Mv0tZiLep1_move_range",
                "current": "Ranged (20 ft)",
                "max": "",
                "id": "-MvWiYEm_jovuRkYpie8"
            },
            {
                "name": "repeating_moves_-MvWiV2UP-Mv0tZiLep1_move_type",
                "current": "ghost",
                "max": "",
                "id": "-MvWiYISu1LNqQ26oZjZ"
            },
            {
                "name": "repeating_moves_-MvWiV2UP-Mv0tZiLep1_move_totaldamage",
                "current": 11,
                "max": "",
                "id": "-MvWiYKTN5xHl2JThlgo"
            },
            {
                "name": "repeating_moves_-MvWiV2UP-Mv0tZiLep1_move_totaldamage_display",
                "current": "3d10 + 11",
                "max": "",
                "id": "-MvWiYKZAiqncSI_oqhg"
            },
            {
                "name": "repeating_moves_-MvWiV2UP-Mv0tZiLep1_move_category",
                "current": "2",
                "max": "",
                "id": "-MvWiYWD-0d6ZPanpTZz"
            },
            {
                "name": "repeating_moves_-MvWiV2UP-Mv0tZiLep1_move_category_defense",
                "current": "Special Defense",
                "max": "",
                "id": "-MvWiYYB_Hd0pnxfo2_K"
            },
            {
                "name": "repeating_moves_-MvWiV2UP-Mv0tZiLep1_move_totalaccuracy",
                "current": 7,
                "max": "",
                "id": "-MvWiYYUX1giDJ59y3Op"
            },
            {
                "name": "repeating_moves_-MvWiV2UP-Mv0tZiLep1_move_totalaccuracy_display",
                "current": "d20 + 7",
                "max": "",
                "id": "-MvWiYYZ6g3PSJcsWxVZ"
            },
            {
                "name": "repeating_moves_-MvWiV2UP-Mv0tZiLep1_move_frequency",
                "current": "1day",
                "max": "",
                "id": "-MvWiYpZZdmVHWV2_mrv"
            },
            {
                "name": "repeating_moves_-MvWiV2UP-Mv0tZiLep1_move_dicenumber",
                "current": "3",
                "max": "",
                "id": "-MvWiZ-MHqumhWvyfWe4"
            },
            {
                "name": "repeating_moves_-MvWiV2UP-Mv0tZiLep1_damage_dice",
                "current": "10",
                "max": "",
                "id": "-MvWiaKLhX6yR3_jrpVr"
            },
            {
                "name": "repeating_moves_-MvWiV2UP-Mv0tZiLep1_move_effect",
                "current": "On hit, the target’s Special Defense is -1 for 10 mins. This effect cannot be stacked.",
                "max": "",
                "id": "-MvWidj2fQbv7z6xGnfU"
            },
            {
                "name": "repeating_moves_-MvWiV2UP-Mv0tZiLep1_options_flag",
                "current": "0",
                "max": "",
                "id": "-MvWih6RWW6ae53USn2Q"
            },
            {
                "name": "repeating_moves_-MvWiV2UP-Mv0tZiLep1_flag",
                "current": "+",
                "max": "",
                "id": "-MvWih8eyek0NrHV5WTf"
            },
            {
                "name": "repeating_moves_-MvWihJzSFILhvYZmtMj_move_name",
                "current": "Aromatherapy",
                "max": "",
                "id": "-MvWiiOQHK3MJQcKQn_e"
            },
            {
                "name": "repeating_moves_-MvWihJzSFILhvYZmtMj_move_usage",
                "current": "0",
                "max": "",
                "id": "-MvWiiUCwi71tVFBsGRt"
            },
            {
                "name": "repeating_moves_-MvWihJzSFILhvYZmtMj_move_range",
                "current": "Melee",
                "max": "",
                "id": "-MvWij6URGnxfxi9Hu6j"
            },
            {
                "name": "repeating_moves_-MvWihJzSFILhvYZmtMj_move_type",
                "current": "grass",
                "max": "",
                "id": "-MvWijEeFaz5klLro2dz"
            },
            {
                "name": "repeating_moves_-MvWihJzSFILhvYZmtMj_move_totaldamage",
                "current": 0,
                "max": "",
                "id": "-MvWijGnj4A4ZpykRRXt"
            },
            {
                "name": "repeating_moves_-MvWihJzSFILhvYZmtMj_move_totaldamage_display",
                "current": "0",
                "max": "",
                "id": "-MvWijGsOGW1mWzZCtGB"
            },
            {
                "name": "repeating_moves_-MvWihJzSFILhvYZmtMj_move_category",
                "current": "3",
                "max": "",
                "id": "-MvWijawVVuMOEFOc2VX"
            },
            {
                "name": "repeating_moves_-MvWihJzSFILhvYZmtMj_move_category_defense",
                "current": "Speed",
                "max": "",
                "id": "-MvWijcznjzd8BYn-Dc2"
            },
            {
                "name": "repeating_moves_-MvWihJzSFILhvYZmtMj_move_totalaccuracy",
                "current": 3,
                "max": "",
                "id": "-MvWijd4WVKr-6VQuDPM"
            },
            {
                "name": "repeating_moves_-MvWihJzSFILhvYZmtMj_move_totalaccuracy_display",
                "current": "d20 + 3",
                "max": "",
                "id": "-MvWijd8R8ffu9co5J54"
            },
            {
                "name": "repeating_moves_-MvWihJzSFILhvYZmtMj_move_frequency",
                "current": "1day",
                "max": "",
                "id": "-MvWiji-v3vnhWMpR-1l"
            },
            {
                "name": "repeating_moves_-MvWihJzSFILhvYZmtMj_move_dicenumber",
                "current": "0",
                "max": "",
                "id": "-MvWikrt8wpg7i8hwImC"
            },
            {
                "name": "repeating_moves_-MvWihJzSFILhvYZmtMj_move_effect",
                "current": "Target an ally or yourself. Target is cured of all afflictions.",
                "max": "",
                "id": "-MvWjAHeub73yRYhd08G"
            },
            {
                "name": "repeating_moves_-MvWihJzSFILhvYZmtMj_options_flag",
                "current": "0",
                "max": "",
                "id": "-MvWjAJslTRIiNFAEqV7"
            },
            {
                "name": "repeating_moves_-MvWihJzSFILhvYZmtMj_flag",
                "current": "+",
                "max": "",
                "id": "-MvWjALqiOlmkzvVGn3d"
            },
            {
                "name": "repeating_moves_-MvWiLfNCOhDyxWI97iG_move_effect1_name",
                "current": "",
                "max": "",
                "id": "-Mxs7cIQaUtAi_gQSzN-"
            },
            {
                "name": "repeating_moves_-MvWiLfNCOhDyxWI97iG_move_effect2_name",
                "current": "",
                "max": "",
                "id": "-Mxs7cITznWhrwU0D6VD"
            },
            {
                "name": "repeating_moves_-MvWiV2UP-Mv0tZiLep1_move_effect1_name",
                "current": "",
                "max": "",
                "id": "-Mxs7cIUqGxhNoLIjz7V"
            },
            {
                "name": "repeating_moves_-MvWiV2UP-Mv0tZiLep1_move_effect2_name",
                "current": "",
                "max": "",
                "id": "-Mxs7cIWjMfrBmhxGslz"
            },
            {
                "name": "repeating_moves_-MvWihJzSFILhvYZmtMj_move_effect1_name",
                "current": "",
                "max": "",
                "id": "-Mxs7cIYtp41mQ9eenjt"
            },
            {
                "name": "repeating_moves_-MvWihJzSFILhvYZmtMj_move_effect2_name",
                "current": "",
                "max": "",
                "id": "-Mxs7cIZBkh35dVwW3DP"
            },
            {
                "name": "pokemon_sex",
                "current": "Gender unknown",
                "max": "",
                "id": "-Mxs7sURRzvs9QDzak1q"
            }
        ],
        "abilities": []
    }
}