{
    "schema_version": 3,
    "type": "character",
    "character": {
        "oldId": "-Mw3yYRL1FaJLlpL9BJQ",
        "name": "Stonjourner",
        "avatar": "https://s3.amazonaws.com/files.d20.io/images/275860303/s81dXYluFL2zOMrrAhRUzw/med.jpg?1647426030",
        "bio": "%3Cp%3EStonjourner%20are%20mysterious%20Pok%E9mon%20that%2C%20despite%20being%20Rock%0A-types%2C%20are%20rarely%20found%20anywhere%20near%20actual%20sources%20of%20stone.%0AInstead%2C%20they%20prefer%20to%20dwell%20on%20open%20grasslands%20and%20ancient%0Aruins.%20Stonjourner%20have%20a%20peculiar%20habit%20of%20watching%20the%20sun%20for%0Along%20stretches%20of%20time.%20All%20Stonjourner%20will%20at%20the%20very%20least%20observe%20the%20sun%20at%20its%20zenith%20as%20well%20as%20when%20it%20reaches%20horizon.%0AOnce%20a%20year%2C%20Stonjourner%20across%20the%20globe%20will%20journey%20to%20specific%0Aareas%20of%20the%20world%20and%20stand%20together%2C%20motionless%2C%20in%20circles.%0AThis%20event%20occurs%20at%20a%20specific%20date%20and%20time%20that%20all%20individuals%0Aseem%20to%20know%20regardless%20of%20time%20zones%2C%20weather%2C%20or%20other%20factors.%20They%20will%20remain%20this%20way%20until%20the%20sun%20sets%2C%20and%20then%20disperse%20as%20if%20nothing%20had%20happened.%20Though%20they%20initially%20appear%0Aimmobile%2C%20Stonjourner%20can%20deliver%20very%20powerful%20kicks%20with%20their%0Ahuge%2C%20stony%20legs%3B%20they%20dislike%20being%20interrupted%20from%20their%20sungazing%20and%20will%20retaliate%20this%20way%20if%20bothered.%3C/p%3E",
        "gmnotes": "",
        "defaulttoken": "",
        "tags": "[\"Rock\",\"Grassland\",\"Ruin\"]",
        "controlledby": "",
        "inplayerjournals": "",
        "attribs": [
            {
                "name": "atknature",
                "current": 0,
                "max": "",
                "id": "-Mw3yrxojYeXmh7FbDBU"
            },
            {
                "name": "defnature",
                "current": 0,
                "max": "",
                "id": "-Mw3yrxtIGfkbRK0tc5n"
            },
            {
                "name": "spatknature",
                "current": 0,
                "max": "",
                "id": "-Mw3yrxxhcEpsEBfTo3r"
            },
            {
                "name": "spdefnature",
                "current": 0,
                "max": "",
                "id": "-Mw3yry-I8PRoT_1Je1Q"
            },
            {
                "name": "spdnature",
                "current": 0,
                "max": "",
                "id": "-Mw3yry4kRjb6318MYYN"
            },
            {
                "name": "afflictions_text",
                "current": "",
                "max": "",
                "id": "-Mw3yrzLq2KEFywRzGOW"
            },
            {
                "name": "capture_total",
                "current": 4,
                "max": "",
                "id": "-Mw3yrzabjb3-D2hIi8x"
            },
            {
                "name": "capture_display",
                "current": "+5",
                "max": "",
                "id": "-Mw3yrzda45lg18c7FEs"
            },
            {
                "name": "capture_roll_total",
                "current": 5,
                "max": "",
                "id": "-Mw3yrzfco16L1lz63WF"
            },
            {
                "name": "nature",
                "current": 0,
                "max": "",
                "id": "-Mw3ys-5_qtBNvXlgXq1"
            },
            {
                "name": "nature-type",
                "current": "0",
                "max": "",
                "id": "-Mw3ys-89M7suUztp4Ug"
            },
            {
                "name": "atkbase",
                "current": "13",
                "max": "",
                "id": "-Mw3ys-Bzw_8VWdrnQvY"
            },
            {
                "name": "defbase",
                "current": "14",
                "max": "",
                "id": "-Mw3ys-EZF2MP7Jh4bw5"
            },
            {
                "name": "spatkbase",
                "current": "2",
                "max": "",
                "id": "-Mw3ys-HzTDV3-YF4SOn"
            },
            {
                "name": "spdefbase",
                "current": "2",
                "max": "",
                "id": "-Mw3ys-JVp_OpqlLvTho"
            },
            {
                "name": "spdbase",
                "current": "9",
                "max": "",
                "id": "-Mw3ys-KO0XGuh-vKvza"
            },
            {
                "name": "acrobatics_total",
                "current": 4,
                "max": "",
                "id": "-Mw3ys-gz8Qt9z7J1YrP"
            },
            {
                "name": "athletics_total",
                "current": 6,
                "max": "",
                "id": "-Mw3ys-i749xy8E0F-cC"
            },
            {
                "name": "bluff_total",
                "current": 1,
                "max": "",
                "id": "-Mw3ys-kPscdiaZYvD22"
            },
            {
                "name": "concentration_total",
                "current": 7,
                "max": "",
                "id": "-Mw3ys-mWZJwWoAtt5N4"
            },
            {
                "name": "constitution_total",
                "current": 7,
                "max": "",
                "id": "-Mw3ys-qOdkIJgfmft4K"
            },
            {
                "name": "diplomacy_total",
                "current": 1,
                "max": "",
                "id": "-Mw3ys-tPmpEv_aZ4FBE"
            },
            {
                "name": "engineering_total",
                "current": 1,
                "max": "",
                "id": "-Mw3ys-xXZmPT42zWEn3"
            },
            {
                "name": "history_total",
                "current": 1,
                "max": "",
                "id": "-Mw3ys0EwVotokfbnV2u"
            },
            {
                "name": "insight_total",
                "current": 1,
                "max": "",
                "id": "-Mw3ys0UxbbxHSDotsAr"
            },
            {
                "name": "investigate_total",
                "current": 1,
                "max": "",
                "id": "-Mw3ys0kpDGtAJCZq9Nx"
            },
            {
                "name": "medicine_total",
                "current": 1,
                "max": "",
                "id": "-Mw3ys1-FSxOZj0oeK84"
            },
            {
                "name": "nature_total",
                "current": 1,
                "max": "",
                "id": "-Mw3ys1FytueXIupibpo"
            },
            {
                "name": "perception_total",
                "current": 1,
                "max": "",
                "id": "-Mw3ys1Y7ao6KYTce6E5"
            },
            {
                "name": "perform_total",
                "current": 1,
                "max": "",
                "id": "-Mw3ys1ouUYiv8Eg6bEu"
            },
            {
                "name": "handling_total",
                "current": 1,
                "max": "",
                "id": "-Mw3ys2EtcQ20sQ2FbH8"
            },
            {
                "name": "programming_total",
                "current": 1,
                "max": "",
                "id": "-Mw3ys2IHZ_NcuGvrGvI"
            },
            {
                "name": "sleightofhand_total",
                "current": 4,
                "max": "",
                "id": "-Mw3ys2_8UwAehZNqDUl"
            },
            {
                "name": "stealth_total",
                "current": 4,
                "max": "",
                "id": "-Mw3ys2oN1Pqm-W80c2z"
            },
            {
                "name": "selected-page",
                "current": "configuration-page",
                "max": "",
                "id": "-Mw3yxqYmlg5doyGZc5_"
            },
            {
                "name": "character-type",
                "current": "pokemon",
                "max": "",
                "id": "-Mw3yyAxpaa2ktpjbkmM"
            },
            {
                "name": "species",
                "current": "Stonjourner",
                "max": "",
                "id": "-Mw3z-g8IXQ1uXpVKwCP"
            },
            {
                "name": "type1",
                "current": "rock",
                "max": "",
                "id": "-Mw3z-gYh6dX58xbMjOI"
            },
            {
                "name": "size",
                "current": "Huge",
                "max": "",
                "id": "-Mw3z0IcC6jtVCwT4jAC"
            },
            {
                "name": "weight",
                "current": "Superweight",
                "max": "",
                "id": "-Mw3z0s5-GkytpqRvQAU"
            },
            {
                "name": "egg_group",
                "current": "Mineral-20 days",
                "max": "",
                "id": "-Mw3zbXQhrTh1CmGgflH"
            },
            {
                "name": "diet",
                "current": "Phototroph/Terravore",
                "max": "",
                "id": "-Mw3zg44I2qnNpf7jp0C"
            },
            {
                "name": "HP",
                "current": "60",
                "max": "60",
                "id": "-Mw3zhiDHUEeSfR1hP4t"
            },
            {
                "name": "ATK",
                "current": 13,
                "max": "",
                "id": "-Mw3ziZ0_vhavGfMmw_G"
            },
            {
                "name": "ATKMOD",
                "current": 6,
                "max": "",
                "id": "-Mw3ziZ6m6Q2QTAKWfjS"
            },
            {
                "name": "DEF",
                "current": 14,
                "max": "",
                "id": "-Mw3zizBXCS8xIITYbuX"
            },
            {
                "name": "DEFMOD",
                "current": 7,
                "max": "",
                "id": "-Mw3zizDPJr9vwx6VYRC"
            },
            {
                "name": "SPATK",
                "current": 2,
                "max": "",
                "id": "-Mw3zjCHrEm4dxhsnUS3"
            },
            {
                "name": "SPATKMOD",
                "current": 1,
                "max": "",
                "id": "-Mw3zjCJIHM2rShPdoMA"
            },
            {
                "name": "SPDEF",
                "current": 2,
                "max": "",
                "id": "-Mw3zjLD-pGPFKFXniLR"
            },
            {
                "name": "SPDEFMOD",
                "current": 1,
                "max": "",
                "id": "-Mw3zjLFwyVCufY6sQ2O"
            },
            {
                "name": "SPD",
                "current": 9,
                "max": "",
                "id": "-Mw3zj_kFzE3FxqsxFaR"
            },
            {
                "name": "SPDMOD",
                "current": 4,
                "max": "",
                "id": "-Mw3zj_lufqik-i3EUah"
            },
            {
                "name": "movement",
                "current": 45,
                "max": "",
                "id": "-Mw3zj_noARsny8JT3vc"
            },
            {
                "name": "pokemonskills",
                "current": "Sinker (can’t swim)",
                "max": "",
                "id": "-Mw3znIO6jqfxpbGG7rK"
            },
            {
                "name": "statpassives",
                "current": "Rock Polish (+2 Speed)",
                "max": "",
                "id": "-Mw3ztEmWoOyuZ933XoW"
            },
            {
                "name": "otherpassives",
                "current": "Power Spot (Attacks made within 10ft of you deal +4 damage, regardless if the attacker is friend or foe.)\n",
                "max": "",
                "id": "-Mw4-DLqsmEA3TqHeY3U"
            },
            {
                "name": "repeating_moves_-Mw4-DYdYE7M2e-k3Bqs_move_name",
                "current": "Stomp",
                "max": "",
                "id": "-Mw4-EC_CSYsnK36PHmv"
            },
            {
                "name": "repeating_moves_-Mw4-DYdYE7M2e-k3Bqs_move_usage",
                "current": "0",
                "max": "",
                "id": "-Mw4-EIH4GYmHDdjRomw"
            },
            {
                "name": "repeating_moves_-Mw4-DYdYE7M2e-k3Bqs_move_range",
                "current": "Melee",
                "max": "",
                "id": "-Mw4-EvOBmD_Y_PHIDg7"
            },
            {
                "name": "repeating_moves_-Mw4-DYdYE7M2e-k3Bqs_move_category",
                "current": "1",
                "max": "",
                "id": "-Mw4-FBo9g-9chSTtgIj"
            },
            {
                "name": "repeating_moves_-Mw4-DYdYE7M2e-k3Bqs_move_category_defense",
                "current": "Defense",
                "max": "",
                "id": "-Mw4-FDTcN8K9wEkOf7_"
            },
            {
                "name": "repeating_moves_-Mw4-DYdYE7M2e-k3Bqs_move_totaldamage",
                "current": 6,
                "max": "",
                "id": "-Mw4-FDYeSKOI565wOyI"
            },
            {
                "name": "repeating_moves_-Mw4-DYdYE7M2e-k3Bqs_move_totaldamage_display",
                "current": "2d8 + 6",
                "max": "",
                "id": "-Mw4-FDaDc3UIUIDWuzB"
            },
            {
                "name": "repeating_moves_-Mw4-DYdYE7M2e-k3Bqs_move_totalaccuracy",
                "current": 6,
                "max": "",
                "id": "-Mw4-FDe40SsGFvqHv72"
            },
            {
                "name": "repeating_moves_-Mw4-DYdYE7M2e-k3Bqs_move_totalaccuracy_display",
                "current": "d20 + 6",
                "max": "",
                "id": "-Mw4-FDhFztw191OAulu"
            },
            {
                "name": "repeating_moves_-Mw4-DYdYE7M2e-k3Bqs_move_frequency",
                "current": "atwill",
                "max": "",
                "id": "-Mw4-FIXGNYsJTNTcTCt"
            },
            {
                "name": "repeating_moves_-Mw4-DYdYE7M2e-k3Bqs_move_dicenumber",
                "current": "2",
                "max": "",
                "id": "-Mw4-FcdPimYRBeRObbU"
            },
            {
                "name": "repeating_moves_-Mw4-DYdYE7M2e-k3Bqs_damage_dice",
                "current": "8",
                "max": "",
                "id": "-Mw4-FhSGahv_58vWUKY"
            },
            {
                "name": "repeating_moves_-Mw4-DYdYE7M2e-k3Bqs_move_effect",
                "current": "On hit, if you got 18 or higher on Accuracy Check, the target is Stunned.",
                "max": "",
                "id": "-Mw4-Nw49lshDYxx_oOd"
            },
            {
                "name": "repeating_moves_-Mw4-DYdYE7M2e-k3Bqs_move_effect1_threshold",
                "current": "18",
                "max": "",
                "id": "-Mw4-ODjj1_KFndTegfw"
            },
            {
                "name": "repeating_moves_-Mw4-DYdYE7M2e-k3Bqs_move_effect1",
                "current": "10",
                "max": "",
                "id": "-Mw4-OIfFvXStVmIGzxu"
            },
            {
                "name": "repeating_moves_-Mw4-DYdYE7M2e-k3Bqs_move_effect1_name",
                "current": "Stunned",
                "max": "",
                "id": "-Mw4-OKKcGczMymj9g9v"
            },
            {
                "name": "repeating_moves_-Mw4-DYdYE7M2e-k3Bqs_move_effect2_name",
                "current": "",
                "max": "",
                "id": "-Mw4-OKLKXE1sxuVbfKT"
            },
            {
                "name": "repeating_moves_-Mw4-DYdYE7M2e-k3Bqs_options_flag",
                "current": "0",
                "max": "",
                "id": "-Mw4-OmRcmdMzNf0Bwf1"
            },
            {
                "name": "repeating_moves_-Mw4-DYdYE7M2e-k3Bqs_flag",
                "current": "+",
                "max": "",
                "id": "-Mw4-Oo6-12yjJ7u1h-R"
            },
            {
                "name": "repeating_moves_-Mw4-P-rWjTNJqiZGQXV_move_name",
                "current": "Stealth Rock",
                "max": "",
                "id": "-Mw4-P_EJp9XYegCr38z"
            },
            {
                "name": "repeating_moves_-Mw4-P-rWjTNJqiZGQXV_move_usage",
                "current": "0",
                "max": "",
                "id": "-Mw4-QahQeBvg6iE4fAv"
            },
            {
                "name": "repeating_moves_-Mw4-P-rWjTNJqiZGQXV_move_range",
                "current": "Ranged (5 ft)",
                "max": "",
                "id": "-Mw4-S0SObmTy8StKC98"
            },
            {
                "name": "repeating_moves_-Mw4-P-rWjTNJqiZGQXV_move_type",
                "current": "rock",
                "max": "",
                "id": "-Mw4-SARa0Qy8qzg46l9"
            },
            {
                "name": "repeating_moves_-Mw4-P-rWjTNJqiZGQXV_move_totaldamage",
                "current": 0,
                "max": "",
                "id": "-Mw4-SCNqbxtq6luSDNm"
            },
            {
                "name": "repeating_moves_-Mw4-P-rWjTNJqiZGQXV_move_totaldamage_display",
                "current": "0",
                "max": "",
                "id": "-Mw4-SCQbxErXNZBVXq7"
            },
            {
                "name": "repeating_moves_-Mw4-P-rWjTNJqiZGQXV_move_category",
                "current": "3",
                "max": "",
                "id": "-Mw4-SKJ3XshixsThMd2"
            },
            {
                "name": "repeating_moves_-Mw4-P-rWjTNJqiZGQXV_move_category_defense",
                "current": "Speed",
                "max": "",
                "id": "-Mw4-SMBs0Z3EbPgf4rK"
            },
            {
                "name": "repeating_moves_-Mw4-P-rWjTNJqiZGQXV_move_totalaccuracy",
                "current": 4,
                "max": "",
                "id": "-Mw4-SMDoZnXoYpcZ5Hk"
            },
            {
                "name": "repeating_moves_-Mw4-P-rWjTNJqiZGQXV_move_totalaccuracy_display",
                "current": "d20 + 4",
                "max": "",
                "id": "-Mw4-SMFShgnYCG2G6n-"
            },
            {
                "name": "repeating_moves_-Mw4-P-rWjTNJqiZGQXV_move_frequency",
                "current": "1day",
                "max": "",
                "id": "-Mw4-SQOaymCNya16ymT"
            },
            {
                "name": "repeating_moves_-Mw4-P-rWjTNJqiZGQXV_move_effect",
                "current": "Place a Stealth Rock Hazard adjacent to you. Stealth Rock Hazard has the following ability: If a foe moves within 20 ft of Stealth Rock Hazard, it will hurl itself at the foe, destroying itself and dealing 2d12 Rock-type damage to the foe without needing an Accuracy Check. This Hazard disappears after 2 mins.",
                "max": "",
                "id": "-Mw4-WyueJFKV_1x1coB"
            },
            {
                "name": "repeating_moves_-Mw4-P-rWjTNJqiZGQXV_options_flag",
                "current": "0",
                "max": "",
                "id": "-Mw4-X-RHZaV1Vb8pzZy"
            },
            {
                "name": "repeating_moves_-Mw4-P-rWjTNJqiZGQXV_flag",
                "current": "+",
                "max": "",
                "id": "-Mw4-X1MsVAswLThIH1o"
            },
            {
                "name": "repeating_moves_-Mw4-XExw-20M8CsG7bK_move_name",
                "current": "Stone Edge",
                "max": "",
                "id": "-Mw4-XxDDx-oUeneKnJB"
            },
            {
                "name": "repeating_moves_-Mw4-XExw-20M8CsG7bK_move_usage",
                "current": "0",
                "max": "",
                "id": "-Mw4-Y25duIudxxg4MDK"
            },
            {
                "name": "repeating_moves_-Mw4-XExw-20M8CsG7bK_move_range",
                "current": "Ranged (25 ft)",
                "max": "",
                "id": "-Mw4-Z865eVdNXLbubYv"
            },
            {
                "name": "repeating_moves_-Mw4-XExw-20M8CsG7bK_move_type",
                "current": "rock",
                "max": "",
                "id": "-Mw4-ZBRITAQkGQQyvwW"
            },
            {
                "name": "repeating_moves_-Mw4-XExw-20M8CsG7bK_move_totaldamage",
                "current": 10,
                "max": "",
                "id": "-Mw4-ZDQo3mIPBT0cHlQ"
            },
            {
                "name": "repeating_moves_-Mw4-XExw-20M8CsG7bK_move_totaldamage_display",
                "current": "5d12 + 10",
                "max": "",
                "id": "-Mw4-ZDSBxIcInE2E68m"
            },
            {
                "name": "repeating_moves_-Mw4-XExw-20M8CsG7bK_move_category",
                "current": "1",
                "max": "",
                "id": "-Mw4-ZJ0MO8Raa5UemJc"
            },
            {
                "name": "repeating_moves_-Mw4-XExw-20M8CsG7bK_move_category_defense",
                "current": "Defense",
                "max": "",
                "id": "-Mw4-ZKnoAIPM8d1uqPE"
            },
            {
                "name": "repeating_moves_-Mw4-XExw-20M8CsG7bK_move_totalaccuracy",
                "current": 4,
                "max": "",
                "id": "-Mw4-ZKuvuST3-zxvHbw"
            },
            {
                "name": "repeating_moves_-Mw4-XExw-20M8CsG7bK_move_totalaccuracy_display",
                "current": "d20 + 4",
                "max": "",
                "id": "-Mw4-ZKyYxo0gfwy_4_z"
            },
            {
                "name": "repeating_moves_-Mw4-XExw-20M8CsG7bK_move_frequency",
                "current": "3day",
                "max": "",
                "id": "-Mw4-ZR1_FN7WTwYUweM"
            },
            {
                "name": "repeating_moves_-Mw4-XExw-20M8CsG7bK_move_dicenumber",
                "current": "5",
                "max": "",
                "id": "-Mw4-ZbYmTGNYbkopKDo"
            },
            {
                "name": "repeating_moves_-Mw4-XExw-20M8CsG7bK_damage_dice",
                "current": "12",
                "max": "",
                "id": "-Mw4-ZgL7BimRd_B7mNv"
            },
            {
                "name": "repeating_moves_-Mw4-XExw-20M8CsG7bK_move_effect",
                "current": "Stone Edge has -2 during Accuracy Check. On hit, if you got 18 or higher on Accuracy Check, Stone Edge is a critical hit.",
                "max": "",
                "id": "-Mw4-c1qII6CbDF1hsjV"
            },
            {
                "name": "repeating_moves_-Mw4-XExw-20M8CsG7bK_move_acmod",
                "current": "-2",
                "max": "",
                "id": "-Mw4-ciiEDuSO133cuv3"
            },
            {
                "name": "repeating_moves_-Mw4-XExw-20M8CsG7bK_move_effect1_threshold",
                "current": "18",
                "max": "",
                "id": "-Mw4-dYv4Dgoc9Krz-yM"
            },
            {
                "name": "repeating_moves_-Mw4-XExw-20M8CsG7bK_move_effect1",
                "current": "99",
                "max": "",
                "id": "-Mw4-dnAOpsQJTz7l89H"
            },
            {
                "name": "repeating_moves_-Mw4-XExw-20M8CsG7bK_move_effect1_name",
                "current": "",
                "max": "",
                "id": "-Mw4-doz3ixnYLX8zQIt"
            },
            {
                "name": "repeating_moves_-Mw4-XExw-20M8CsG7bK_move_effect2_name",
                "current": "",
                "max": "",
                "id": "-Mw4-dp0L22qcGVMDoLO"
            },
            {
                "name": "repeating_moves_-Mw4-XExw-20M8CsG7bK_options_flag",
                "current": "0",
                "max": "",
                "id": "-Mw4-eAZqurVzjTvShKn"
            },
            {
                "name": "repeating_moves_-Mw4-XExw-20M8CsG7bK_flag",
                "current": "+",
                "max": "",
                "id": "-Mw4-eCUTRsjjtGkfXYs"
            },
            {
                "name": "notes",
                "current": "Proficiencies: Ground / Rock / Kicks",
                "max": "",
                "id": "-Mw4-hv_QhpaHDqa3LvH"
            },
            {
                "name": "repeating_moves_-Mw4-P-rWjTNJqiZGQXV_move_effect1_name",
                "current": "",
                "max": "",
                "id": "-MyHEVKzs2xiaTS7K9qV"
            },
            {
                "name": "repeating_moves_-Mw4-P-rWjTNJqiZGQXV_move_effect2_name",
                "current": "",
                "max": "",
                "id": "-MyHEVL4jH2IW947cbRR"
            },
            {
                "name": "pokemon_sex",
                "current": "50% male, 50% female",
                "max": "",
                "id": "-MyHEnGtb_H8ZKzboBzb"
            }
        ],
        "abilities": []
    }
}